Workbook

Sheet transmittal
C3: NATIONAL FOOD AUTHORITY
C5: Caraga Regional Office (Region XV)
C6: _____________________________________________________________________________________________________
C7: NFA Compound, Libertad, Butuan City 8600 www.nfa.gov.ph
A10: 44308
A13: FOR : | B13: ELSA ASUNCION LIM
B14: Acting Department Manager
B15: Internal Audit Department
A17: FROM: | B17: NFA- Caraga Regional Office
A19: SUBJECT: | B19: INVENTORY AND AUDIT OF PROPERTY, PLANT AND EQUIPMENT OF
B20: NFA CARAGA REGIONAL OFFICE
A23: In reference to Memorandum coded AO-2021-03-018 dated 15 March 2021, we are submitting our
A24: Inventory and Audit of Property, Plant and Equipment as follows:
A26: 1. Accomplished Inventory Report of PPE ( Annex 1) and
A27: 2. Pictures of the PPE.
A29: These are for your references. Thank you.
A33: OSMUNDO R. GUINTO JR.
A34: OIC- Regional Manager

Sheet RPCPPE
Q1: Appendix 73
B2: NATIONAL FOOD AUTHORITY - CARAGA
B3: Regional Office No. XV
B4: As of Dec. 31, 2025
B6: REPORT ON THE PHYSICAL COUNT OF PROPERTY, PLANT AND EQUIPMENT
B8: ARTICLE / ITEM | C8: Date Acquired | D8: DESCRIPTION | E8: PROPERTY NO. | F8: SERIAL NUMBER | G8: DATE ACQUIRED | H8: UNIT OF MEA. | I8: UNIT VALUE | J8: QTY PER PROP. CARD | K8: ACCOUNTABLE OFFICER | L8: LOCATION | M8: CONDITION | N8: QTY PER PHYSICAL COUNT | O8: SHORTAGE/ OVERAGE | Q8: REMARKS | R8: PHOTO LINK
O9: QTY | P9: VALUE
B10: BUILDING
C11: 43462 | D11: Building - Regional Office | E11: 2018-NFA-00B-BS-A-0028.5 | G11: 43462 | I11: 1782828.5 | J11: 1 | K11: HYDE BETH M. PASCUAL | L11: Libertad Compound | M11: Good Condition | N11: 1 | O11: 0 | P11: 0 | R11: 1.jpg
C12: 28858 | D12: Building - Regional Office | E12: 1979-NFA-002-BS-A-001 | G12: 28915 | I12: 1476980.1 | J12: 1 | K12: HYDE BETH M. PASCUAL | L12: J. Rosales Ave., Bxu | M12: Good Condition | N12: 1 | O12: 0 | P12: 0
F13: Sub Total | I13: =SUM(I11:I12) -> 3259808.6
B14: COMMUNICATION EQUIPMENT
D15: Video Conferencing System TV SN:5204942, PC DELL - DJNY6K3, LOGITECH RALLY PLUS (TABLE HUB, DISPLAY HUB, CAMERA, MIC POS 1 & 2 SPEAKER L&R) | E15: 2022-NFA-MSD-CM-G-021 | G15: 44564 | H15: set | I15: 305103.38 | J15: 1 | K15: HYDE BETH M. PASCUAL | L15: Conference Room | M15: Good Condition | N15: 1 | O15: 0 | P15: 0
D16: DJI AIR 2S DRONE FLY MORE COMBO BUNDLE Inclusion: Aircraft, Remote Controller, Flight Battery, Charging Hub, Power Adapter, Travel Bag, AC Power Cable, USB Cable, ND Filters | E16: 2023-NFA-00B-CM-I-001 | G16: 45208 | H16: set | I16: 77137 | J16: 1 | K16: ROEL D. CAPERIG | L16: Supply Room | M16: Good Condition | N16: 1 | O16: 0 | P16: 0
D17: Yamaha DBR12 2-WAY, BI AMP POWERED SPEAKER | E17: 2024-NFA-00B-CM-G-001 | F17: EFDZ01077 | G17: 45640 | H17: unit | I17: 53000 | J17: 1 | K17: ROEL D. CAPERIG | L17: RO Lobby | M17: Good Condition | N17: 1 | O17: 0 | P17: 0
D18: Yamaha DBR12 2-WAY, BI AMP POWERED SPEAKER | E18: 2024-NFA-00B-CM-G-002 | F18: EFDZ01078 | G18: 45640 | H18: unit | I18: 53000 | J18: 1 | K18: ROEL D. CAPERIG | L18: RO Lobby | M18: Good Condition | N18: 1 | O18: 0 | P18: 0
D19: TELEVISION, LED, 75 INCHES SONY | E19: 2024-NFA-OOB-CM-G-001 | G19: 45653 | H19: unit | I19: 70092 | J19: 1 | K19: HYDE BETH M. PASCUAL | L19: RO Lobby | M19: Good Condition | N19: 1
F20: Sub Total | I20: =SUM(I15:I19) -> 558332.38
B21: IT EQUIPMENT AND SOFTWARE
C22: 01/04/2007 | D22: SERVER, HP PROLIANT (UPGRADED) | E22: 2007-NFA-002-DP-F-001 | F22: ML350G4 | G22: 39086 | H22: pc. | I22: 244431.05 | J22: 1 | K22: ROEL D. CAPERIG | L22: Common Storage Room (Libertad) | M22: Unserviceable | N22: 1 | O22: 0 | P22: 0 | Q22: IIRUP NO. CAR-IIR-2022-C-001 | R22: 50.jpg
D23: B3-420 Notebook 14" Core15-1135g7 / 16B DDR4 / 512GB NVME PCI-E SSD, Intel IRIS XE Graphics, SN# JEXPM22325000059 | E23: 2022-NFA-MSD-DP-T-059 | F23: JEXPM22325000059 | G23: 44883 | H23: set | I23: 56400 | J23: 1 | K23: ANTONIO ROSARIO U. LAGRIMAS | L23: RM's Office | M23: Good Condition | N23: 1 | O23: 0 | P23: 0
D24: SYNOLOGY DS923+ 4BAY DISKSTATION NETWORK ATTACHED STORAGE (NAS) WITH 4PCS NAS 3.5" SATA HARDRIVE AND 16GB SODIMM MEMORY | E24: 2023-NFA-00B-DP-B-001 | G24: 45127 | H24: set | I24: 70670 | J24: 1 | K24: ROEL D. CAPERIG | L24: Regional Office | M24: Good Condition | N24: 1 | O24: 0 | P24: 0
D25: EPSON L15150 A3 Wi-Fi Duplex All-in-One Ink Tank | E25: 2024-NFA-00B-DP-D-001 | G25: 45617 | H25: unit | I25: 51345 | J25: 1 | K25: ROBERT BACANGGOY | L25: FM Section | M25: Good Condition | N25: 1 | O25: 0 | P25: 0
F26: Sub Total | I26: =SUM(I22:I25) -> 422846.05
B27: FURNITURE, FIXTURES & BOOKS
D28: =UPPER("12 seater T-shape Conference Table") -> 12 SEATER T-SHAPE CONFERENCE TABLE | E28: 2022-NFA-00B-FF-D-001 | G28: 44208 | H28: set | I28: 97500 | J28: 1 | K28: HYDE BETH M. PASCUAL | L28: Conference Room | M28: Good Condition | N28: 1 | O28: 0 | P28: 0
D29: SOFA SET | E29: 2023-NFA-00B-FF-I-003 | G29: 45093 | H29: set | I29: 62000 | J29: 1 | K29: HYDE BETH M. PASCUAL | L29: RO Lobby | M29: Good Condition | N29: 1 | O29: 0 | P29: 0
D30: WINDOW BLINDS (Blue) | E30: 2023-NFA-00B-FF-L-003 | G30: 45148 | H30: set | I30: 83650 | J30: 1 | K30: HYDE BETH M. PASCUAL | L30: Regional Office | M30: Good Condition | N30: 1 | O30: 0 | P30: 0
D31: SOFA SET (2 Seater & 3 Seater) | E31: 2024-NFA-00B-FF-I-001 | G31: 45588 | H31: set | I31: 59752 | J31: 1 | K31: HYDE BETH M. PASCUAL | L31: ARM's Office | M31: Good Condition | N31: 1 | O31: 0 | P31: 0
D32: DINING CHAIRS, SIX (6) PCS, GRAY COLOR | E32: 2024-NFA-00B-FF-c-001 | G32: 45588 | H32: set | I32: 65970 | J32: 1 | K32: HYDE BETH M. PASCUAL | L32: RO Lobby | M32: Good Condition | N32: 1 | O32: 0 | P32: 0
F33: Sub Total | I33: =SUM(I28:I32) -> 368872
A34: 8 | B34: MOTOR VEHICLES, LAND TRANS. EQUIPT AND ACCESORIES
C35: 38737 | D35: TOYOTA INNOVA DSL MODEL 2005 ENGINE # 2KD-9547460 | E35: 2006-NFA-GSD-LT-C-132 | G35: 38737 | H35: unit | I35: 848000 | J35: 1 | K35: JESON JARIOL | L35: Regional Office | M35: Good Condition | N35: 1 | O35: 0 | P35: 0 | R35: 63.jpg
C36: 42636 | D36: ISUZU CROSSWIND SPORTIVO ENGINE # 4JA1M57459 CHASSIS # PABTBBR54FG2089995 | E36: 2016-NFA-GSD-LT-C-203 | G36: 42636 | H36: unit | I36: 1180000 | J36: 1 | K36: JOJIT J. CASIO | L36: Regional Office | M36: Good Condition | N36: 1 | O36: 0 | P36: 0 | R36: 64.jpg
D37: 2021 MITSUBISHI STRADA GLS 2.4D 2WD, 4N15UHC6103 SILVER METALIC, AT | E37: 2021-NFA-GSD-LT-C-229 | G37: 44439 | H37: unit | I37: 1397400 | J37: 1 | K37: ALEXIS M. RAVELO | L37: Regional Office | M37: Good Condition | N37: 1 | O37: 0 | P37: 0
F38: Sub Total | I38: =SUM(I35:I37) -> 3425400
B39: OFFICE EQUIPMENT | O39: 0 | P39: 0
C40: 01/11/2012 | D40: ROOM AIRCONDITIONER, SPLIT TYPE-WALL MOUNTED, 2.0 HP, W/ INVERTER , PANASONIC | E40: 2012-NFA-0B0-OE-C-010 | F40: 2486201743 | G40: 40919 | H40: set | I40: 55000 | J40: 1 | K40: ROEL D. CAPERIG | L40: Common Storage Room (Libertad) | M40: Unserviceable | N40: 1 | O40: 0 | P40: 0 | Q40: for IIRUP | R40: 71.jpg
C41: 41269 | D41: AIRCONDITIONER , PACKED TYPE-FLOOR MOUNTED , 3 TONS, KOPPEL | E41: 2012-NFA-0B0-OE-C-011 | F41: UE323210 | G41: 41269 | H41: set | I41: 81600 | J41: 1 | K41: ROEL D. CAPERIG | L41: Common Storage Room (Libertad) | M41: Unserviceable | N41: 1 | O41: 0 | P41: 0 | Q41: for IIRUP | R41: 72.jpg
C42: 41269 | D42: AIRCONDITIONER , PACKED TYPE-FLOOR MOUNTED , 3 TONS, KOPPEL | E42: 2012-NFA-0B0-OE-C-013 | F42: KE248331 | G42: 41269 | H42: set | I42: 81600 | J42: 1 | K42: ROEL D. CAPERIG | L42: Common Storage Room (Libertad) | M42: Unserviceable | N42: 1 | O42: 0 | P42: 0 | Q42: for IIRUP | R42: 74.jpg
C43: 42718 | D43: CHILLER, 2 DOOR SHOWCASE TYPE, CAPACITY 1,000 LTRS | E43: 2016-NFA-00B-OE-T-003 | G43: 42718 | H43: set | I43: 68000 | J43: 1 | K43: GERLIZA L. MULA | L43: QAS Section | M43: Good Condition | N43: 1 | O43: 0 | P43: 0 | R43: 87.jpg
D44: KOPPEL 3.0 TR FLOOR MOUNTED INVERTER | E44: 2022-NFA-00B-OE-C-020 | G44: 44656 | H44: set | I44: 106000 | J44: 1 | K44: HYDE BETH M. PASCUAL | L44: Old RO Office | M44: Good Condition | N44: 1 | O44: 0 | P44: 0 | Q44: Libertad Staffhouse
D45: KOPPEL 3.0 TR FLOOR MOUNTED INVERTER SUPER INVERTER | E45: 2023-NFA-00B-OE-C-022 | G45: 45106 | H45: set | I45: 106610 | J45: 1 | K45: HYDE BETH M. PASCUAL | L45: Old RO Office | M45: Good Condition | N45: 1 | O45: 0 | P45: 0 | Q45: Libertad Staffhouse
D46: KOPPEL 3.0 TR FLOOR MOUNTED INVERTER SUPER INVERTER | E46: 2024-NFA-00B-OE-C-002 | F46: 540P328930145160820099 | G46: 45587 | H46: set | I46: 104140 | J46: 1 | K46: HYDE BETH M. PASCUAL | L46: RO Lobby | M46: Good Condition | N46: 1 | O46: 0 | P46: 0
D47: KOPPEL 3.0 TR FLOOR MOUNTED INVERTER SUPER INVERTER | E47: 2024-NFA-00B-OE-C-003 | F47: 540Q092660248200820069 | G47: 45636 | H47: set | I47: 105500 | J47: 1 | K47: HYDE BETH M. PASCUAL | L47: RO Lobby | M47: Good Condition | N47: 1 | O47: 0 | P47: 0
D48: 24.5 CU. FT. INVERTER SIDE BY SIDE REFRIGERATOR | E48: 2025-NFA-00B-OE-T-001 | F48: 411TRDPDV970 | G48: 45807 | H48: unit | I48: 57288 | J48: 1 | K48: HYDE BETH M. PASCUAL | L48: RO Lobby | M48: Good Condition | N48: 1 | O48: 0 | P48: 0
F49: Sub Total | I49: =SUM(I40:I48) -> 765738
B50: TECHNICAL & SCIENTIFIC EQUIPMENT EQUIPMENT
C51: 08/23/2006 | D51: OHAUS ANALYTICAL BALANCE ADVENTURE 210G X 0.1 MODEL :AR 2140 | E51: 2006-NFA-00B-TS-D-001 | F51: 1227070326 | G51: 38952 | H51: pc. | I51: 80590 | J51: 1 | K51: GERLIZA L. MULA | L51: QAS Section | M51: Good Condition | N51: 1 | O51: 0 | P51: 0 | R51: 93.jpg
C52: 09/27/2007 | D52: OVEN LABORATORY FOR DRYING BINDER BRAND, GERMANY MODEL;ED 53 | E52: 2007-NFA-TRD-TS-D-315 | F52: 07-17295 | G52: 39352 | H52: pc. | I52: 55000 | J52: 1 | K52: GERLIZA L. MULA | L52: QAS Section | M52: Good Condition | N52: 1 | O52: 0 | P52: 0 | R52: 100.jpg
C53: 02/21/2011 | D53: LABORATORY SAMPLE GRINDER ROMER MILL SERIES W/ ACCESSORIES | E53: 2011-NFA-TRD-TS-D-1163 | F53: 10050233 | G53: 40595 | H53: pc. | I53: 299500 | J53: 1 | K53: GERLIZA L. MULA | L53: QAS Section | M53: Good Condition | N53: 1 | O53: 0 | P53: 0 | R53: 97.jpg
C54: 05/02/2017 | D54: ANALYTICAL BALANCE CAPACITY 220G X 0.1MG (BRAND: OHAUS) | E54: 2017-NFA-TRS-TS-D-703 | G54: 42857 | H54: pc. | I54: 63930 | J54: 1 | K54: GERLIZA L. MULA | L54: QAS Section | M54: Good Condition | N54: 1 | O54: 0 | P54: 0 | R54: 101.jpg
C55: 41591 | D55: LABORATORY POLISHING MACHINE W/ BASIC TOOLS ACCESSORIES | E55: 2013-NFA-TRS-TS-P-008 | F55: S6704/29 | G55: 41591 | H55: set | I55: 248000 | J55: 1 | K55: GERLIZA L. MULA | L55: QAS Section | M55: Good Condition | N55: 1 | O55: 0 | P55: 0 | R55: 104.jpg
C56: 8/13/2021 | D56: LABORATORY POLISHING MACHINE | E56: 2021-NFA-OCD-TS-P-025 | F56: G2003053 | G56: 44421 | H56: set | I56: 471744 | J56: 1 | K56: GERLIZA L. MULA | L56: QAS Section | M56: Good Condition | N56: 1 | O56: 0 | P56: 0
C57: 11/24/2021 | D57: LABORATORY HULLER | E57: 2021-NFA-TRS-TS-D-1221 | F57: CB00406 | G57: 44524 | H57: set | I57: 285600 | J57: 1 | K57: GERLIZA L. MULA | L57: QAS Section | M57: Good Condition | N57: 1 | O57: 0 | P57: 0
D58: YAMAHA DTX452K 5-PIECE ELECTRONIC DRUM KIT | E58: 2024-NFA-00B-TS-H-001 | G58: 45642 | H58: set | I58: 55000 | J58: 1 | K58: ROEL D. CAPERIG | M58: Good Condition | N58: 1 | O58: 0 | P58: 0
D59: Grain Moisture Meter, Model: PM450 Kett with Hardcase | E59: 2025-NFA-00B-TS-C-001 | F59: CD22157 | G59: 46014 | H59: unit | I59: 112000 | J59: 1 | K59: ROEL D. CAPERIG | L59: QAS Section | M59: Good Condition | N59: 1 | O59: 0 | P59: 0
D60: Grain Moisture Meter Biasing Kit (Software, RS232 Cable, Maintainance Cable VZC-49, MSI Laptop 15.6" FHD Core i5 512gb SSD S/N K2406N0050944) | E60: 2025-NFA-00B-TS-C-001.1 | G60: 46014 | H60: set | I60: 0 | J60: 1 | K60: ROBERT BACANGGOY | L60: FM Section | M60: Good Condition | N60: 1 | O60: 0 | P60: 0
D61: Grain Moisture Meter, Model: PM450 Kett with Hardcase | E61: 2025-NFA-00B-TS-C-002 | F61: CD22158 | G61: 46014 | H61: unit | I61: 112000 | J61: 1 | K61: ROEL D. CAPERIG | L61: Supply Room | M61: Good Condition | N61: 1 | O61: 0 | P61: 0
D62: Grain Moisture Meter, Model: PM450 Kett with Hardcase | E62: 2025-NFA-00B-TS-C-003 | F62: CD22159 | G62: 46014 | H62: unit | I62: 112000 | J62: 1 | K62: ROEL D. CAPERIG | L62: Supply Room | M62: Good Condition | N62: 1 | O62: 0 | P62: 0
D63: Grain Moisture Meter, Model: PM450 Kett with Hardcase | E63: 2025-NFA-00B-TS-C-004 | F63: CD22160 | G63: 46014 | H63: unit | I63: 112000 | J63: 1 | K63: ROEL D. CAPERIG | L63: Supply Room | M63: Good Condition | N63: 1 | O63: 0 | P63: 0
D64: Grain Moisture Meter, Model: PM450 Kett with Hardcase | E64: 2025-NFA-00B-TS-C-005 | F64: CD22161 | G64: 46014 | H64: unit | I64: 112000 | J64: 1 | K64: ROEL D. CAPERIG | L64: Supply Room | M64: Good Condition | N64: 1 | O64: 0 | P64: 0
D65: Grain Moisture Meter, Model: PM450 Kett with Hardcase | E65: 2025-NFA-00B-TS-C-006 | F65: CD22162 | G65: 46014 | H65: unit | I65: 112000 | J65: 1 | K65: ROEL D. CAPERIG | L65: Supply Room | M65: Good Condition | N65: 1 | O65: 0 | P65: 0
D66: Grain Moisture Meter, Model: PM450 Kett with Hardcase | E66: 2025-NFA-00B-TS-C-007 | F66: CD22163 | G66: 46014 | H66: unit | I66: 112000 | J66: 1 | K66: ROEL D. CAPERIG | L66: Supply Room | M66: Good Condition | N66: 1 | O66: 0 | P66: 0
D67: Grain Moisture Meter, Model: PM450 Kett with Hardcase | E67: 2025-NFA-00B-TS-C-008 | F67: CD22164 | G67: 46014 | H67: unit | I67: 112000 | J67: 1 | K67: ROEL D. CAPERIG | L67: Supply Room | M67: Good Condition | N67: 1 | O67: 0 | P67: 0
D68: Grain Moisture Meter, Model: PM450 Kett with Hardcase | E68: 2025-NFA-00B-TS-C-009 | F68: CD22165 | G68: 46014 | H68: unit | I68: 112000 | J68: 1 | K68: ROEL D. CAPERIG | L68: Supply Room | M68: Good Condition | N68: 1 | O68: 0 | P68: 0
D69: Grain Moisture Meter, Model: PM450 Kett with Hardcase | E69: 2025-NFA-00B-TS-C-010 | F69: CD22166 | G69: 46014 | H69: unit | I69: 112000 | J69: 1 | K69: ROEL D. CAPERIG | L69: Supply Room | M69: Good Condition | N69: 1 | O69: 0 | P69: 0
F70: Sub Total | I70: =SUM(I51:I69) -> 2679364
B71: PLANT MACHINERY & EQUIPMENT
C72: 1/24/2011 | D72: =UPPER("Generator Set Kubota") -> GENERATOR SET KUBOTA | E72: 2013-NFA-00B-PE-V-002 | G72: 41275 | H72: set | I72: 439700 | J72: 1 | K72: ROBERT BACANGGOY | L72: GenSet House | M72: Unserviceable | N72: 1 | O72: 0 | P72: 0 | Q72: for IIRUP
D73: Mechanical Platform Scale, Model DB1T, 1000 Capacity | E73: 2025-NFA-00B-WE-D-011 | F73: 250201 | G73: 45973 | H73: set | I73: 87800 | J73: 1 | K73: ROEL D. CAPERIG | L73: Libertad Compound | M73: Good Condition | N73: 1 | O73: 0 | P73: 0
D74: Mechanical Platform Scale, Model DB1T, 1000 Capacity | E74: 2025-NFA-00B-WE-D-012 | F74: 250202 | G74: 45973 | H74: set | I74: 87800 | J74: 1 | K74: ROEL D. CAPERIG | L74: Libertad Compound | M74: Good Condition | N74: 1 | O74: 0 | P74: 0
D75: Mechanical Platform Scale, Model DB1T, 1000 Capacity | E75: 2025-NFA-00B-WE-D-013 | F75: 250203 | G75: 45973 | H75: set | I75: 87800 | J75: 1 | K75: ROEL D. CAPERIG | L75: Libertad Compound | M75: Good Condition | N75: 1 | O75: 0 | P75: 0
D76: Mechanical Platform Scale, Model DB1T, 1000 Capacity | E76: 2025-NFA-00B-WE-D-014 | F76: 250204 | G76: 45973 | H76: set | I76: 87800 | J76: 1 | K76: ROEL D. CAPERIG | L76: Libertad Compound | M76: Good Condition | N76: 1 | O76: 0 | P76: 0
D77: Mechanical Platform Scale, Model DB1T, 1000 Capacity | E77: 2025-NFA-00B-WE-D-015 | F77: 250205 | G77: 45973 | H77: set | I77: 87800 | J77: 1 | K77: ROEL D. CAPERIG | L77: Libertad Compound | M77: Good Condition | N77: 1 | O77: 0 | P77: 0
D78: Mechanical Platform Scale, Model DB1T, 1000 Capacity | E78: 2025-NFA-00B-WE-D-016 | F78: 250206 | G78: 45973 | H78: set | I78: 87800 | J78: 1 | K78: ROEL D. CAPERIG | L78: Libertad Compound | M78: Good Condition | N78: 1 | O78: 0 | P78: 0
D79: Mechanical Platform Scale, Model DB1T, 1000 Capacity | E79: 2025-NFA-00B-WE-D-017 | F79: 250207 | G79: 45973 | H79: set | I79: 87800 | J79: 1 | K79: ROEL D. CAPERIG | L79: Libertad Compound | M79: Good Condition | N79: 1 | O79: 0 | P79: 0
D80: Mechanical Platform Scale, Model DB1T, 1000 Capacity | E80: 2025-NFA-00B-WE-D-018 | F80: 250208 | G80: 45973 | H80: set | I80: 87800 | J80: 1 | K80: ROEL D. CAPERIG | L80: Libertad Compound | M80: Good Condition | N80: 1 | O80: 0 | P80: 0
D81: Mechanical Platform Scale, Model DB1T, 1000 Capacity | E81: 2025-NFA-00B-WE-D-019 | F81: 250209 | G81: 45973 | H81: set | I81: 87800 | J81: 1 | K81: ROEL D. CAPERIG | L81: Libertad Compound | M81: Good Condition | N81: 1 | O81: 0 | P81: 0
D82: Mechanical Platform Scale, Model DB1T, 1000 Capacity | E82: 2025-NFA-00B-WE-D-020 | F82: 250210 | G82: 45973 | H82: set | I82: 87800 | J82: 1 | K82: ROEL D. CAPERIG | L82: Libertad Compound | M82: Good Condition | N82: 1 | O82: 0 | P82: 0
D83: Mechanical Platform Scale, Model DB1T, 1000 Capacity | E83: 2025-NFA-00B-WE-D-021 | F83: 250301 | G83: 45973 | H83: set | I83: 87800 | J83: 1 | K83: ROEL D. CAPERIG | L83: Libertad Compound | M83: Good Condition | N83: 1 | O83: 0 | P83: 0
D84: Mechanical Platform Scale, Model DB1T, 1000 Capacity | E84: 2025-NFA-00B-WE-D-022 | F84: 250302 | G84: 45973 | H84: set | I84: 87800 | J84: 1 | K84: ROEL D. CAPERIG | L84: Libertad Compound | M84: Good Condition | N84: 1 | O84: 0 | P84: 0
... D87: Mechanical Platform Scale, Model DB1T, 1000 Capacity | E87: 2025-NFA-00B-WE-D-025 | F87: 250305 | G87: 45973 | H87: set | I87: 87800 | J87: 1 | K87: ROEL D. CAPERIG | L87: Libertad Compound | M87: Good Condition | N87: 1 | O87: 0 | P87: 0
F88: Sub Total | I88: =SUM(I72:I87) -> 1756700
I89: =+I13+I20+I26+I33+I38+I49+I70+I88 -> 13237061
D91: Certified Correct by: | G91: Approved by: | M91: Verified by:
D94: HYDE BETH M. PASCUAL | G94: ANTONIO ROSARIO U. LAGRIMAS II
D95: SAO | G95: Regional Manager II | M95: COA Representative

Sheet Caperig-1
A3: Republic of the Philippines
A4: NATIONAL FOOD AUTHORITY
A5: Caraga Regional Office
A7: PROPERTY ACKNOWLEDGEMENT RECEIPT
A9: DATE : | B9: =TODAY() -> 46037
A10: PAR Number : | B10: 1500-2024-001
A12: PROPERTY NUMBER | B12: QTY | C12: UNIT | D12: ITEM DESCRIPTION | E12: UNIT COST | F12: TOTAL COST | G12: E.U.L | H12: DATE ACQUIRED
A13: =+RPCPPE!#REF! -> #REF! | B13: =+RPCPPE!#REF! -> #REF! | C13: =+RPCPPE!#REF! -> #REF! | D13: =+RPCPPE!#REF! -> #REF! | E13: =+RPCPPE!#REF! -> #REF! | F13: =+E13 -> #REF! | G13: 5 | H13: =+RPCPPE!#REF! -> #REF!
A14: =+RPCPPE!E16 -> 2023-NFA-00B-CM-I-001 | B14: =+RPCPPE!N16 -> 1 | C14: =+RPCPPE!H16 -> set | D14: =+RPCPPE!D16 -> DJI AIR 2S DRONE FLY MORE COMBO BUNDLE Inclusion: Aircraft, Remote Controller, Flight Battery, Charging Hub, Power Adapter, Travel Bag, AC Power Cable, USB Cable, ND Filters | E14: =+RPCPPE!I16 -> 77137 | F14: =+E14 -> 77137 | G14: 5 | H14: =+RPCPPE!G16 -> 45208
A15: =+RPCPPE!E22 -> 2007-NFA-002-DP-F-001 | B15: =+RPCPPE!N22 -> 1 | C15: =+RPCPPE!H22 -> pc. | D15: =+RPCPPE!D22 -> SERVER, HP PROLIANT (UPGRADED) | E15: =+RPCPPE!I22 -> 244431.05 | F15: =+E15 -> 244431.05 | G15: 5 | H15: =+RPCPPE!G22 -> 39086
A16: =+RPCPPE!E24 -> 2023-NFA-00B-DP-B-001 | B16: =+RPCPPE!N24 -> 1 | C16: =+RPCPPE!H24 -> set | D16: =+RPCPPE!D24 -> SYNOLOGY DS923+ 4BAY DISKSTATION NETWORK ATTACHED STORAGE (NAS) WITH 4PCS NAS 3.5" SATA HARDRIVE AND 16GB SODIMM MEMORY | E16: =+RPCPPE!I24 -> 70670 | F16: =+E16 -> 70670 | G16: 5 | H16: =+RPCPPE!G24 -> 45127
A17: =+RPCPPE!#REF! -> #REF! | B17: =+RPCPPE!#REF! -> #REF! | C17: =+RPCPPE!#REF! -> #REF! | D17: =+RPCPPE!#REF! -> #REF! | E17: =+RPCPPE!#REF! -> #REF! | F17: =+E17 -> #REF! | G17: 5 | H17: =+RPCPPE!#REF! -> #REF!
D18: xxxNothing Followsxxx
A30: RECEIVED FROM: | D30: RECEIVED BY: | E30: APPROVED BY:
A33: ROEL D. CAPERIG | D33: =+A33 -> ROEL D. CAPERIG | E33: REJORIE R. ONDE
A34: PMO IV | D34: =+A34 -> PMO IV | E34: OIC Regional Manager

Sheet Mendoza-2
A3: Republic of the Philippines
A4: NATIONAL FOOD AUTHORITY
A5: Caraga Regional Office
A7: PROPERTY ACKNOWLEDGEMENT RECEIPT
A9: DATE : | B9: =TODAY() -> 46037
A10: PAR Number : | B10: 1500-2024-002
A12: PROPERTY NUMBER | B12: QTY | C12: UNIT | D12: ITEM DESCRIPTION | E12: UNIT COST | F12: TOTAL COST | G12: E.U.L | H12: DATE ACQUIRED
A13: =+RPCPPE!E11 -> 2018-NFA-00B-BS-A-0028.5 | B13: =+RPCPPE!N11 -> 1 | C13: =+RPCPPE!H11 -> 0 | D13: =+RPCPPE!D11 -> Building - Regional Office | E13: =+RPCPPE!I11 -> 1782828.5 | F13: =+E13 -> 1782828.5 | G13: 30 | H13: =+RPCPPE!G11 -> 43462
A14: =+RPCPPE!E12 -> 1979-NFA-002-BS-A-001 | B14: =+RPCPPE!N12 -> 1 | C14: =+RPCPPE!H12 -> 0 | D14: =+RPCPPE!D12 -> Building - Regional Office | E14: =+RPCPPE!I12 -> 1476980.1 | F14: =+E14 -> 1476980.1 | G14: 30 | H14: =+RPCPPE!G12 -> 28915
A15: =+RPCPPE!E15 -> 2022-NFA-MSD-CM-G-021 | B15: =+RPCPPE!N15 -> 1 | C15: =+RPCPPE!H15 -> set | D15: =+RPCPPE!D15 -> Video Conferencing System TV SN:5204942, PC DELL - DJNY6K3, LOGITECH RALLY PLUS (TABLE HUB, DISPLAY HUB, CAMERA, MIC POS 1 & 2 SPEAKER L&R) | E15: =+RPCPPE!I15 -> 305103.38 | F15: =+E15 -> 305103.38 | G15: 5 | H15: =+RPCPPE!G15 -> 44564
A16: =+RPCPPE!E16 -> 2023-NFA-00B-CM-I-001 | B16: =+RPCPPE!N16 -> 1 | C16: =+RPCPPE!H16 -> set | D16: =+RPCPPE!D16 -> DJI AIR 2S DRONE FLY MORE COMBO BUNDLE Inclusion: Aircraft, Remote Controller, Flight Battery, Charging Hub, Power Adapter, Travel Bag, AC Power Cable, USB Cable, ND Filters | E16: =+RPCPPE!I16 -> 77137 | F16: =+E16 -> 77137 | G16: 5 | H16: 1/1/2018
A17: =+RPCPPE!E28 -> 2022-NFA-00B-FF-D-001 | B17: =+RPCPPE!N28 -> 1 | C17: =+RPCPPE!H28 -> set | D17: =+RPCPPE!D28 -> 12 SEATER T-SHAPE CONFERENCE TABLE | E17: =+RPCPPE!I28 -> 97500 | F17: =+E17 -> 97500 | G17: 5 | H17: =+RPCPPE!G28 -> 44208
A18: =+RPCPPE!E29 -> 2023-NFA-00B-FF-I-003 | B18: =+RPCPPE!N29 -> 1 | C18: =+RPCPPE!H29 -> set | D18: =+RPCPPE!D29 -> SOFA SET | E18: =+RPCPPE!I29 -> 62000 | F18: =+E18 -> 62000 | G18: 3 | H18: =+RPCPPE!G29 -> 45093
A19: =+RPCPPE!E30 -> 2023-NFA-00B-FF-L-003 | B19: =+RPCPPE!N30 -> 1 | C19: =+RPCPPE!H30 -> set | D19: =+RPCPPE!D30 -> WINDOW BLINDS (Blue) | E19: =+RPCPPE!I30 -> 83650 | F19: =+E19 -> 83650 | G19: 5 | H19: =+RPCPPE!G30 -> 45148
A20: =+RPCPPE!E41 -> 2012-NFA-0B0-OE-C-011 | B20: =+RPCPPE!N41 -> 1 | C20: =+RPCPPE!H41 -> set | D20: =+RPCPPE!D41 -> AIRCONDITIONER , PACKED TYPE-FLOOR MOUNTED , 3 TONS, KOPPEL | E20: =+RPCPPE!I41 -> 81600 | F20: =+E20 -> 81600 | G20: 3 | H20: =+RPCPPE!G41 -> 41269
A21: =+RPCPPE!E42 -> 2012-NFA-0B0-OE-C-013 | B21: =+RPCPPE!N42 -> 1 | C21: =+RPCPPE!H42 -> set | D21: =+RPCPPE!D42 -> AIRCONDITIONER , PACKED TYPE-FLOOR MOUNTED , 3 TONS, KOPPEL | E21: =+RPCPPE!I42 -> 81600 | F21: =+E21 -> 81600 | G21: 3 | H21: =+RPCPPE!G42 -> 41269
A22: =+RPCPPE!E44 -> 2022-NFA-00B-OE-C-020 | B22: =+RPCPPE!N44 -> 1 | C22: =+RPCPPE!H44 -> set | D22: =+RPCPPE!D44 -> KOPPEL 3.0 TR FLOOR MOUNTED INVERTER | E22: =+RPCPPE!I44 -> 106000 | F22: =+E22 -> 106000 | G22: 3 | H22: =+RPCPPE!G44 -> 44656
A23: =+RPCPPE!E45 -> 2023-NFA-00B-OE-C-022 | B23: =+RPCPPE!N45 -> 1 | C23: =+RPCPPE!H45 -> set | D23: =+RPCPPE!D45 -> KOPPEL 3.0 TR FLOOR MOUNTED INVERTER SUPER INVERTER | E23: =+RPCPPE!I45 -> 106610 | F23: =+E23 -> 106610 | G23: 3 | H23: =+RPCPPE!G45 -> 45106
A24: RECEIVED FROM: | D24: RECEIVED BY: | E24: APPROVED BY:
A27: ROEL D. CAPERIG | D27: AMIELOU JANE G. MENDOZA | E27: REJORIE R. ONDE
A28: PMO IV | D28: Acting SAO | E28: OIC Regional Manager

Sheet Mula-3
A3: Republic of the Philippines
A4: NATIONAL FOOD AUTHORITY
A5: Caraga Regional Office
A7: PROPERTY ACKNOWLEDGEMENT RECEIPT
A9: DATE : | B9: =TODAY() -> 46037
A10: PAR Number : | B10: 1500-2024-003
A12: PROPERTY NUMBER | B12: QTY | C12: UNIT | D12: ITEM DESCRIPTION | E12: UNIT COST | F12: TOTAL COST | G12: E.U.L | H12: DATE ACQUIRED
A13: =+RPCPPE!E43 -> 2016-NFA-00B-OE-T-003 | B13: =+RPCPPE!N43 -> 1 | C13: =+RPCPPE!H43 -> set | D13: =+RPCPPE!D43 -> CHILLER, 2 DOOR SHOWCASE TYPE, CAPACITY 1,000 LTRS | E13: =+RPCPPE!I43 -> 68000 | F13: =+E13 -> 68000 | G13: 5 | H13: =+RPCPPE!G43 -> 42718
A14: =+RPCPPE!E51 -> 2006-NFA-00B-TS-D-001 | B14: =+RPCPPE!N51 -> 1 | C14: =+RPCPPE!H51 -> pc. | D14: =+RPCPPE!D51 -> OHAUS ANALYTICAL BALANCE ADVENTURE 210G X 0.1 MODEL :AR 2140 | E14: =+RPCPPE!I51 -> 80590 | F14: =+E14 -> 80590 | G14: 5 | H14: =+RPCPPE!G51 -> 38952
A15: =+RPCPPE!E52 -> 2007-NFA-TRD-TS-D-315 | B15: =+RPCPPE!N52 -> 1 | C15: =+RPCPPE!H52 -> pc. | D15: =+RPCPPE!D52 -> OVEN LABORATORY FOR DRYING BINDER BRAND, GERMANY MODEL;ED 53 | E15: =+RPCPPE!I52 -> 55000 | F15: =+E15 -> 55000 | G15: 5 | H15: =+RPCPPE!G52 -> 39352
A16: =+RPCPPE!E53 -> 2011-NFA-TRD-TS-D-1163 | B16: =+RPCPPE!N53 -> 1 | C16: =+RPCPPE!H53 -> pc. | D16: =+RPCPPE!D53 -> LABORATORY SAMPLE GRINDER ROMER MILL SERIES W/ ACCESSORIES | E16: =+RPCPPE!I53 -> 299500 | F16: =+E16 -> 299500 | G16: 5 | H16: =+RPCPPE!G53 -> 40595
A17: =+RPCPPE!E54 -> 2017-NFA-TRS-TS-D-703 | B17: =+RPCPPE!N54 -> 1 | C17: =+RPCPPE!H54 -> pc. | D17: =+RPCPPE!D54 -> ANALYTICAL BALANCE CAPACITY 220G X 0.1MG (BRAND: OHAUS) | E17: =+RPCPPE!I54 -> 63930 | F17: =+E17 -> 63930 | G17: 5 | H17: =+RPCPPE!G54 -> 42857
A18: =+RPCPPE!E55 -> 2013-NFA-TRS-TS-P-008 | B18: =+RPCPPE!N55 -> 1 | C18: =+RPCPPE!H55 -> set | D18: =+RPCPPE!D55 -> LABORATORY POLISHING MACHINE W/ BASIC TOOLS ACCESSORIES | E18: =+RPCPPE!I55 -> 248000 | F18: =+E18 -> 248000 | G18: 5 | H18: =+RPCPPE!G55 -> 41591
A19: =+RPCPPE!E56 -> 2021-NFA-OCD-TS-P-025 | B19: =+RPCPPE!N56 -> 1 | C19: =+RPCPPE!H56 -> set | D19: =+RPCPPE!D56 -> LABORATORY POLISHING MACHINE | E19: =+RPCPPE!I56 -> 471744 | F19: =+E19 -> 471744 | G19: 5 | H19: =+RPCPPE!G56 -> 44421
A20: =+RPCPPE!E57 -> 2021-NFA-TRS-TS-D-1221 | B20: =+RPCPPE!N57 -> 1 | C20: =+RPCPPE!H57 -> set | D20: =+RPCPPE!D57 -> LABORATORY HULLER | E20: =+RPCPPE!I57 -> 285600 | F20: =+E20 -> 285600 | G20: 5 | H20: =+RPCPPE!G57 -> 44524
D21: xxxNothing Followsxxx
A27: RECEIVED FROM: | D27: RECEIVED BY: | E27: APPROVED BY:
A30: ROEL D. CAPERIG | D30: GERLIZA L. MULA | E30: REJORIE R. ONDE
A31: PMO IV | D31: RSQAO | E31: OIC Regional Manager

Sheet Jariol-4
A3: Republic of the Philippines
A4: NATIONAL FOOD AUTHORITY
A5: Caraga Regional Office
A7: PROPERTY ACKNOWLEDGEMENT RECEIPT
A9: DATE : | B9: =TODAY() -> 46037
A10: PAR Number : | B10: 1500-2024-004
A12: PROPERTY NUMBER | B12: QTY | C12: UNIT | D12: ITEM DESCRIPTION | E12: UNIT COST | F12: TOTAL COST | G12: E.U.L | H12: DATE ACQUIRED
A13: =+RPCPPE!E35 -> 2006-NFA-GSD-LT-C-132 | B13: =+RPCPPE!N35 -> 1 | C13: =+RPCPPE!H35 -> unit | D13: =+RPCPPE!D35 -> TOYOTA INNOVA DSL MODEL 2005 ENGINE # 2KD-9547460 | E13: =+RPCPPE!I35 -> 848000 | F13: =+E13 -> 848000 | G13: 7 | H13: =+RPCPPE!G35 -> 38737
D14: xxxNothing Followsxxx
A38: RECEIVED FROM: | D38: RECEIVED BY: | E38: APPROVED BY:
A41: ROEL D. CAPERIG | D41: JESON JARIOL | E41: REJORIE R. ONDE
A42: PMO IV | D42: Truck Driver | E42: OIC Regional Manager

Sheet Casio-5
A3: Republic of the Philippines
A4: NATIONAL FOOD AUTHORITY
A5: Caraga Regional Office
A7: PROPERTY ACKNOWLEDGEMENT RECEIPT
A9: DATE : | B9: =TODAY() -> 46037
A10: PAR Number : | B10: 1500-2024-005
A12: PROPERTY NUMBER | B12: QTY | C12: UNIT | D12: ITEM DESCRIPTION | E12: UNIT COST | F12: TOTAL COST | G12: E.U.L | H12: DATE ACQUIRED
A13: =+RPCPPE!E36 -> 2016-NFA-GSD-LT-C-203 | B13: =+RPCPPE!N36 -> 1 | C13: =+RPCPPE!H36 -> unit | D13: =+RPCPPE!D36 -> ISUZU CROSSWIND SPORTIVO ENGINE # 4JA1M57459 CHASSIS # PABTBBR54FG2089995 | E13: =+RPCPPE!I36 -> 1180000 | F13: =+E13 -> 1180000 | G13: 8 | H13: =+RPCPPE!G36 -> 42636
D14: xxxNothing Followsxxx
A38: RECEIVED FROM: | D38: RECEIVED BY: | E38: APPROVED BY:
A41: ROEL D. CAPERIG | D41: JOJIT J. CASIO | E41: REJORIE R. ONDE
A42: PMO IV | D42: Truck Driver | E42: OIC Regional Manager

Sheet Ravelo-6
A3: Republic of the Philippines
A4: NATIONAL FOOD AUTHORITY
A5: Caraga Regional Office
A7: PROPERTY ACKNOWLEDGEMENT RECEIPT
A9: DATE : | B9: =TODAY() -> 46037
A10: PAR Number : | B10: 1500-2024-006
A12: PROPERTY NUMBER | B12: QTY | C12: UNIT | D12: ITEM DESCRIPTION | E12: UNIT COST | F12: TOTAL COST | G12: E.U.L | H12: DATE ACQUIRED
A13: =+RPCPPE!E37 -> 2021-NFA-GSD-LT-C-229 | B13: =+RPCPPE!N37 -> 1 | C13: =+RPCPPE!H37 -> unit | D13: =+RPCPPE!D37 -> 2021 MITSUBISHI STRADA GLS 2.4D 2WD, 4N15UHC6103 SILVER METALIC, AT | E13: =+RPCPPE!I37 -> 1397400 | F13: =+E13 -> 1397400 | G13: 9 | H13: =+RPCPPE!G37 -> 44439
D14: xxxNothing Followsxxx
A38: RECEIVED FROM: | D38: RECEIVED BY: | E38: APPROVED BY:
A41: ROEL D. CAPERIG | D41: ALEXIS M. RAVELO | E41: REJORIE R. ONDE
A42: PMO IV | D42: Truck Driver | E42: OIC Regional Manager

Sheet Awing-7
A3: Republic of the Philippines
A4: NATIONAL FOOD AUTHORITY
A5: Caraga Regional Office
A7: PROPERTY ACKNOWLEDGEMENT RECEIPT
A9: DATE : | B9: =TODAY() -> 46037
A10: PAR Number : | B10: 1500-2024-007
A12: PROPERTY NUMBER | B12: QTY | C12: UNIT | D12: ITEM DESCRIPTION | E12: UNIT COST | F12: TOTAL COST | G12: E.U.L | H12: DATE ACQUIRED
A13: =+RPCPPE!E40 -> 2012-NFA-0B0-OE-C-010 | B13: =+RPCPPE!N40 -> 1 | C13: =+RPCPPE!H40 -> set | D13: =+RPCPPE!D40 -> ROOM AIRCONDITIONER, SPLIT TYPE-WALL MOUNTED, 2.0 HP, W/ INVERTER , PANASONIC | E13: =+RPCPPE!I40 -> 55000 | F13: =+E13 -> 55000 | G13: 3 | H13: =+RPCPPE!G40 -> 40919
D14: xxxNothing Followsxxx
A38: RECEIVED FROM: | D38: RECEIVED BY: | E38: APPROVED BY:
A41: ROEL D. CAPERIG | D41: LOVELLA MAY AWING | E41: REJORIE R. ONDE
A42: PMO IV | D42: Acting Accountant IV | E42: OIC Regional Manager

Sheet Bacanggoy-8
A3: Republic of the Philippines
A4: NATIONAL FOOD AUTHORITY
A5: Caraga Regional Office
A7: PROPERTY ACKNOWLEDGEMENT RECEIPT
A9: DATE : | B9: =TODAY() -> 46037
A10: PAR Number : | B10: 1500-2024-008
A12: PROPERTY NUMBER | B12: QTY | C12: UNIT | D12: ITEM DESCRIPTION | E12: UNIT COST | F12: TOTAL COST | G12: E.U.L | H12: DATE ACQUIRED
A13: =+RPCPPE!E72 -> 2013-NFA-00B-PE-V-002 | B13: =+RPCPPE!N72 -> 1 | C13: =+RPCPPE!H72 -> set | D13: =+RPCPPE!D72 -> GENERATOR SET KUBOTA | E13: =+RPCPPE!I72 -> 439700 | F13: =+E13 -> 439700 | G13: 5 | H13: =+RPCPPE!G72 -> 41275
D14: xxxNothing Followsxxx
A38: RECEIVED FROM: | D38: RECEIVED BY: | E38: APPROVED BY:
A41: ROEL D. CAPERIG | D41: ROBERT BACANGGOY | E41: REJORIE R. ONDE
A42: PMO IV | D42: Engineer III | E42: OIC Regional Manager

Sheet Sabarre-9
A3: Republic of the Philippines
A4: NATIONAL FOOD AUTHORITY
A5: Caraga Regional Office
A7: PROPERTY ACKNOWLEDGEMENT RECEIPT
A9: DATE : | B9: =TODAY() -> 46037
A10: PAR Number : | B10: 1500-2024-009
A12: PROPERTY NUMBER | B12: QTY | C12: UNIT | D12: ITEM DESCRIPTION | E12: UNIT COST | F12: TOTAL COST | G12: E.U.L | H12: DATE ACQUIRED
A13: =+RPCPPE!E23 -> 2022-NFA-MSD-DP-T-059 | B13: =+RPCPPE!N23 -> 1 | C13: =+RPCPPE!H23 -> set | D13: =+RPCPPE!D23 -> B3-420 Notebook 14" Core15-1135g7 / 16B DDR4 / 512GB NVME PCI-E SSD, Intel IRIS XE Graphics, SN# JEXPM22325000059 | E13: =+RPCPPE!I23 -> 56400 | F13: =+E13 -> 56400 | G13: 5 | H13: =+RPCPPE!G23 -> 44883
D14: xxxNothing Followsxxx
A38: RECEIVED FROM: | D38: RECEIVED BY: | E38: APPROVED BY:
A41: ROEL D. CAPERIG | D41: ROBERT BACANGGOY | E41: REJORIE R. ONDE
A42: PMO IV | D42: Engineer III | E42: OIC Regional Manager

Sheet PIF for COA
A2: NATIONAL FOOD AUTHORITY
A3: Caraga Regional Office
A4: J. Rosales Ave., Butuan City
A5: PROPERTY INVENTORY FORM
A6: As of DECEMBER 31 2022
A8: Classification / Type | B8: Item Description | C8: Nature of Occupancy1 | D8: Location | E8: Date Constructed / Acquired / Manufactured | F8: Property No. / Other Reference[2] | G8: Valuation | I8: Date of Appraisal | J8: Remarks
G9: Acquisition Cost/ Insurable Interest2 | H9: Market / Appraisal / Insurable Interest2
A10: (1) | B10: (2) | C10: (3) | D10: (4) | E10: (5) | F10: (6) | G10: (7) | H10: (8) | I10: (9) | J10: (10)
A11: =+RPCPPE!B10 -> BUILDING
B12: =+RPCPPE!D11 -> Building - Regional Office | C12: OFFICE | D12: LIBERTAD COMPOUND | E12: =+RPCPPE!G11 -> 43462 | F12: =+RPCPPE!E11 -> 2018-NFA-00B-BS-A-0028.5 | G12: =+RPCPPE!I11 -> 1782828.5 | H12: =1086117.5+496503 -> 1582620.5 | I12: 44926
B13: =+RPCPPE!D12 -> Building - Regional Office | C13: OFFICE | D13: REGIONAL OFFICE | E13: =+RPCPPE!G12 -> 28915 | F13: =+RPCPPE!E12 -> 1979-NFA-002-BS-A-001 | G13: =+RPCPPE!I12 -> 1476980.1 | H13: =22183.8+12995+5899+17011.81+40564.77+25163.31+24299.4 -> 148117.09 | I13: 44926
B14: Sub-Total | G14: =SUM(G12:G13) -> 3259808.6 | H14: =SUM(H12:H13) -> 1730737.6
A15: =+RPCPPE!B14 -> COMMUNICATION EQUIPMENT
B16: =+RPCPPE!#REF! -> #REF! | C16: OFFICE | D16: REGIONAL OFFICE | F16: =+RPCPPE!#REF! -> #REF! | G16: =+RPCPPE!#REF! -> #REF! | H16: 3149.74 | I16: 44926
B17: =+RPCPPE!D24 -> SYNOLOGY DS923+ 4BAY DISKSTATION NETWORK ATTACHED STORAGE (NAS) WITH 4PCS NAS 3.5" SATA HARDRIVE AND 16GB SODIMM MEMORY | C17: OFFICE | D17: REGIONAL OFFICE | E17: =+RPCPPE!G24 -> 45127 | F17: =+RPCPPE!E24 -> 2023-NFA-00B-DP-B-001 | G17: =+RPCPPE!I24 -> 70670 | H17: 247131.38 | I17: 44926
B18: Sub-Total | G18: =SUM(G16:G17) -> #REF! | H18: =SUM(H16:H17) -> 250281.12
A19: =+RPCPPE!B21 -> IT EQUIPMENT AND SOFTWARE
B20: =+RPCPPE!D22 -> SERVER, HP PROLIANT (UPGRADED) | C20: OFFICE | D20: REGIONAL OFFICE | E20: =+RPCPPE!G22 -> 39086 | F20: =+RPCPPE!E22 -> 2007-NFA-002-DP-F-001 | G20: =+RPCPPE!I22 -> 244431.05 | H20: 12221.56 | I20: 44926
B21: =+RPCPPE!D23 -> B3-420 Notebook 14" Core15-1135g7 / 16B DDR4 / 512GB NVME PCI-E SSD, Intel IRIS XE Graphics, SN# JEXPM22325000059 | C21: OFFICE | D21: REGIONAL OFFICE | E21: =+RPCPPE!G23 -> 44883 | F21: =+RPCPPE!E23 -> 2022-NFA-MSD-DP-T-059 | G21: =+RPCPPE!I23 -> 56400 | H21: 55507 | I21: 44926
B22: =+RPCPPE!#REF! -> #REF! | C22: OFFICE | D22: REGIONAL OFFICE | E22: =+RPCPPE!#REF! -> #REF! | F22: =+RPCPPE!#REF! -> #REF! | G22: =+RPCPPE!#REF! -> #REF! | H22: 2883.26 | I22: 44926
B23: Sub-Total | G23: =SUM(G20:G22) -> #REF! | H23: =SUM(H20:H22) -> 70611.82
A24: =+RPCPPE!B21 -> IT EQUIPMENT AND SOFTWARE
B28: Sub-Total | G28: =SUM(G25:G27) -> 0 | H28: =SUM(H25:H27) -> 0
A29: =+RPCPPE!B27 -> FURNITURE, FIXTURES & BOOKS
B30: =+RPCPPE!#REF! -> #REF! | C30: OFFICE | D30: REGIONAL OFFICE | F30: =+RPCPPE!#REF! -> #REF! | G30: =+RPCPPE!#REF! -> #REF! | H30: 8157.58 | I30: 44926
B31: =+RPCPPE!D30 -> WINDOW BLINDS (Blue) | C31: OFFICE | D31: REGIONAL OFFICE | E31: =+RPCPPE!G30 -> 45148 | F31: =+RPCPPE!E30 -> 2023-NFA-00B-FF-L-003 | G31: =+RPCPPE!I30 -> 83650 | H31: 78872 | I31: 44926
B32: Sub-Total | G32: =SUM(G30:G31) -> #REF! | H32: =SUM(H30:H31) -> 87029.58
A33: =+RPCPPE!B34 -> MOTOR VEHICLES, LAND TRANS. EQUIPT AND ACCESORIES
B34: =+RPCPPE!D35 -> TOYOTA INNOVA DSL MODEL 2005 ENGINE # 2KD-9547460 | C34: OFFICE | D34: REGIONAL OFFICE | E34: =+RPCPPE!G35 -> 38737 | F34: =+RPCPPE!E35 -> 2006-NFA-GSD-LT-C-132 | G34: =+RPCPPE!I35 -> 848000 | H34: =+G34*0.05 -> 42400 | I34: 44926
B35: =+RPCPPE!D36 -> ISUZU CROSSWIND SPORTIVO ENGINE # 4JA1M57459 CHASSIS # PABTBBR54FG2089995 | C35: OFFICE | D35: REGIONAL OFFICE | E35: =+RPCPPE!G36 -> 42636 | F35: =+RPCPPE!E36 -> 2016-NFA-GSD-LT-C-203 | G35: =+RPCPPE!I36 -> 1180000 | H35: 179125 | I35: 44926
B36: =+RPCPPE!D37 -> 2021 MITSUBISHI STRADA GLS 2.4D 2WD, 4N15UHC6103 SILVER METALIC, AT | C36: OFFICE | D36: REGIONAL OFFICE | E36: =+RPCPPE!G37 -> 44439 | F36: =+RPCPPE!E37 -> 2021-NFA-GSD-LT-C-229 | G36: =+RPCPPE!I37 -> 1397400 | H36: 1144536 | I36: 44926
B37: Sub-Total | G37: =SUM(G34:G36) -> 3425400 | H37: =SUM(H34:H36) -> 1366061
A38: =+RPCPPE!B39 -> OFFICE EQUIPMENT
B39: =+RPCPPE!D40 -> ROOM AIRCONDITIONER, SPLIT TYPE-WALL MOUNTED, 2.0 HP, W/ INVERTER , PANASONIC | C39: OFFICE | D39: REGIONAL OFFICE | E39: =+RPCPPE!G40 -> 40919 | F39: =+RPCPPE!E40 -> 2012-NFA-0B0-OE-C-010 | G39: =+RPCPPE!I40 -> 55000 | H39: 2750 | I39: 44926
B40: =+RPCPPE!D41 -> AIRCONDITIONER , PACKED TYPE-FLOOR MOUNTED , 3 TONS, KOPPEL | C40: OFFICE | D40: REGIONAL OFFICE | E40: =+RPCPPE!G41 -> 41269 | F40: =+RPCPPE!E41 -> 2012-NFA-0B0-OE-C-011 | G40: =+RPCPPE!I41 -> 81600 | H40: 4080 | I40: 44926
B41: =+RPCPPE!D42 -> AIRCONDITIONER , PACKED TYPE-FLOOR MOUNTED , 3 TONS, KOPPEL | C41: OFFICE | D41: REGIONAL OFFICE | E41: =+RPCPPE!G42 -> 41269 | F41: =+RPCPPE!E42 -> 2012-NFA-0B0-OE-C-013 | G41: =+RPCPPE!I42 -> 81600 | H41: 4080 | I41: 44926
B42: =+RPCPPE!D43 -> CHILLER, 2 DOOR SHOWCASE TYPE, CAPACITY 1,000 LTRS | C42: OFFICE | D42: REGIONAL OFFICE | E42: =+RPCPPE!G43 -> 42718 | F42: =+RPCPPE!E43 -> 2016-NFA-00B-OE-T-003 | G42: =+RPCPPE!I43 -> 68000 | H42: 3400 | I42: 44926
B43: =+RPCPPE!D44 -> KOPPEL 3.0 TR FLOOR MOUNTED INVERTER | C43: OFFICE | D43: REGIONAL OFFICE | E43: =+RPCPPE!G44 -> 44656 | F43: =+RPCPPE!E44 -> 2022-NFA-00B-OE-C-020 | G43: =+RPCPPE!I44 -> 106000 | H43: 90898 | I43: 44926
B44: Sub-Total | G44: =SUM(G39:G43) -> 392200 | H44: =SUM(H39:H43) -> 105208
A45: =+RPCPPE!B50 -> TECHNICAL & SCIENTIFIC EQUIPMENT EQUIPMENT
B46: =+RPCPPE!D51 -> OHAUS ANALYTICAL BALANCE ADVENTURE 210G X 0.1 MODEL :AR 2140 | C46: OFFICE | D46: REGIONAL OFFICE | E46: =+RPCPPE!G51 -> 38952 | F46: =+RPCPPE!E51 -> 2006-NFA-00B-TS-D-001 | G46: =+RPCPPE!I51 -> 80590 | H46: =+G46*0.05 -> 4029.5 | I46: 44926
B47: =+RPCPPE!D52 -> OVEN LABORATORY FOR DRYING BINDER BRAND, GERMANY MODEL;ED 53 | C47: OFFICE | D47: REGIONAL OFFICE | E47: =+RPCPPE!G52 -> 39352 | F47: =+RPCPPE!E52 -> 2007-NFA-TRD-TS-D-315 | G47: =+RPCPPE!I52 -> 55000 | H47: =+G47*0.05 -> 2750 | I47: 44926
B48: =+RPCPPE!D53 -> LABORATORY SAMPLE GRINDER ROMER MILL SERIES W/ ACCESSORIES | C48: OFFICE | D48: REGIONAL OFFICE | E48: =+RPCPPE!G53 -> 40595 | F48: =+RPCPPE!E53 -> 2011-NFA-TRD-TS-D-1163 | G48: =+RPCPPE!I53 -> 299500 | H48: =+G48*0.05 -> 14975 | I48: 44926
B49: =+RPCPPE!D54 -> ANALYTICAL BALANCE CAPACITY 220G X 0.1MG (BRAND: OHAUS) | C49: OFFICE | D49: REGIONAL OFFICE | E49: =+RPCPPE!G54 -> 42857 | F49: =+RPCPPE!E54 -> 2017-NFA-TRS-TS-D-703 | G49: =+RPCPPE!I54 -> 63930 | H49: 29522 | I49: 44926
B50: =+RPCPPE!D55 -> LABORATORY POLISHING MACHINE W/ BASIC TOOLS ACCESSORIES | C50: OFFICE | D50: REGIONAL OFFICE | E50: =+RPCPPE!G55 -> 41591 | F50: =+RPCPPE!E55 -> 2013-NFA-TRS-TS-P-008 | G50: =+RPCPPE!I55 -> 248000 | H50: 30164 | I50: 44926
B51: =+RPCPPE!D56 -> LABORATORY POLISHING MACHINE | C51: OFFICE | D51: REGIONAL OFFICE | E51: =+RPCPPE!G56 -> 44421 | F51: =+RPCPPE!E56 -> 2021-NFA-OCD-TS-P-025 | G51: =+RPCPPE!I56 -> 471744 | H51: 408249 | I51: 44926
B52: =+RPCPPE!D57 -> LABORATORY HULLER | C52: OFFICE | D52: REGIONAL OFFICE | E52: =+RPCPPE!G57 -> 44524 | F52: =+RPCPPE!E57 -> 2021-NFA-TRS-TS-D-1221 | G52: =+RPCPPE!I57 -> 285600 | H52: 256207 | I52: 44926
B53: Sub-Total | G53: =SUM(G46:G52) -> 1504364 | H53: =SUM(H46:H52) -> 745896.5
A54: =+RPCPPE!B71 -> PLANT MACHINERY & EQUIPMENT
B55: =+RPCPPE!D72 -> GENERATOR SET KUBOTA | C55: OFFICE | D55: REGIONAL OFFICE | E55: 41298 | F55: =+RPCPPE!E72 -> 2013-NFA-00B-PE-V-002 | G55: =+RPCPPE!I72 -> 439700 | H55: 21985 | I55: 44926
B56: Sub-Total | G56: =+G55 -> 439700 | H56: =+H55 -> 21985
B57: TOTAL | G57: =+G14+G18+G23+G32+G37+G44+G53+G56 -> #REF! | H57: =+H14+H18+H23+H32+H37+H44+H53+H56 -> 4377810.6
A58: PART II – OTHER INSURABLE INTERESTS
A59: (a) Rights of Action
A60: (b) Other Insurable Interests
B62: PREPARED BY: | C62: CERTIFIED CORRECT: | F62: APPROVED:
B64: ROEL D. CAPERIG | C64: MARLON O. MARGALLO | F64: VERALEW DG DE VERA
B65: PMO IV | C65: Assistant Regional Manager II | E65: Date | F65: Regional Manager II | I65: Date
B66: Member, Inventory Committee | C66: Head, Inventory Committee | F66: Head of Agency
A68: [1] For buildings and other structures, please indicate the nature or type of occupancy of the Government property whether: schools, offices, clinics, hospitals, laboratories, public markets, car parks, terminals, residential, and other information which are important basis for the pricing of the property and in determining the amount of the premium to be paid to the GSIS.
A69: [2] For insurable interests other than Property.

Sheet AJ Mendoza
Q1: Appendix 73
B2: NATIONAL FOOD AUTHORITY - CARAGA
B3: Regional Office No. XV
B4: As of Dec. 31, 2022
B6: REPORT ON THE PHYSICAL COUNT OF PROPERTY, PLANT AND EQUIPMENT
B7: BUILDING
B9: Fund Cluster: __________
B11: For which, AMIELOU JANE G. MENDOZA - Acting SAO, NFA-Caraga Regional Office is accountable, having assumed such accountability on (________________).
B13: ARTICLE / ITEM | C13: Date Acquired | D13: DESCRIPTION | E13: PROPERTY NO. | F13: SERIAL NUMBER | G13: DATE ACQUIRED | H13: UNIT OF MEA. | I13: UNIT VALUE | J13: QTY PER PROP. CARD | K13: ACCOUNTABLE OFFICER | L13: LOCATION | M13: CONDITION | N13: QTY PER PHYSICAL COUNT | O13: SHORTAGE/ OVERAGE | Q13: REMARKS | R13: PHOTO LINK
O14: QTY | P14: VALUE
B15: BUILDING
C16: 43462 | D16: Building - Regional Office | E16: 2018-NFA-00B-BS-A-0028.5 | G16: 43462 | I16: 1782828.5 | J16: 1 | K16: AMIELOU JANE G. MENDOZA | L16: Libertad Compound, Bxu | M16: Good Condition | N16: 1 | O16: 0 | P16: 0 | R16: 1.jpg
C17: 28858 | D17: Building - Regional Office | E17: 1979-NFA-002-BS-A-001 | G17: 28915 | I17: 1476980.1 | J17: 1 | K17: AMIELOU JANE G. MENDOZA | L17: Libertad Compound, Bxu | M17: Good Condition | N17: 1 | O17: 0 | P17: 0
F26: Sub Total | I26: =SUM(I16:I17) -> 3259808.6
D28: Certified Correct by: | H28: Approved by: | M28: Verified by: | O28: Verified by:
D31: MARLON O. MARGALLO | H31: VERALEW DG. DE VERA
D32: Assistant Regional Manager | H32: Regional Manager II | M32: COA Representative | O32: COA Representative

Sheet AJ Mendoza.CE
Q1: Appendix 73
B2: NATIONAL FOOD AUTHORITY - CARAGA
B3: Regional Office No. XV
B4: As of Dec. 31, 2022
B6: REPORT ON THE PHYSICAL COUNT OF PROPERTY, PLANT AND EQUIPMENT
B7: COMMUNICATION EQUIPMENT
B9: Fund Cluster: __________
B10: For which, AMIELOU JANE G. MENDOZA - Acting SAO, NFA-Caraga Regional Office is accountable, having assumed such accountability on (________________).
B12: ARTICLE / ITEM | C12: Date Acquired | D12: DESCRIPTION | E12: PROPERTY NO. | F12: SERIAL NUMBER | G12: DATE ACQUIRED | H12: UNIT OF MEA. | I12: UNIT VALUE | J12: QTY PER PROP. CARD | K12: ACCOUNTABLE OFFICER | L12: LOCATION | M12: CONDITION | N12: QTY PER PHYSICAL COUNT | O12: SHORTAGE/ OVERAGE | Q12: REMARKS | R12: PHOTO LINK
O13: QTY | P13: VALUE
D14: Video Conferencing System TV SN:5204942, PC DELL - DJNY6K3, LOGITECH RALLY PLUS (TABLE HUB, DISPLAY HUB, CAMERA, MIC POS 1 & 2 SPEAKER L&R) | E14: 2022-NFA-MSD-CM-G-021 | G14: 44564 | H14: set | I14: 305103.38 | J14: 1 | K14: AMIELOU JANE G. MENDOZA | L14: Regional Office | M14: Good Condition | N14: 1 | O14: 0 | P14: 0
D23: Certified Correct by: | H23: Approved by: | M23: Verified by: | O23: Verified by:
D26: MARLON O. MARGALLO | H26: VERALEW DG. DE VERA
D27: Assistant Regional Manager | H27: Regional Manager II | M27: COA Representative | O27: COA Representative

Sheet AJ Mendoza.FFB
Q1: Appendix 73
B2: NATIONAL FOOD AUTHORITY - CARAGA
B3: Regional Office No. XV
B4: As of Dec. 31, 2022
B6: REPORT ON THE PHYSICAL COUNT OF PROPERTY, PLANT AND EQUIPMENT
B7: FURNITURE, FIXTURES & BOOKS
B9: Fund Cluster: __________
B10: For which, AMIELOU JANE G. MENDOZA - Acting SAO, NFA-Caraga Regional Office is accountable, having assumed such accountability on (________________).
B12: ARTICLE / ITEM | C12: Date Acquired | D12: DESCRIPTION | E12: PROPERTY NO. | F12: SERIAL NUMBER | G12: DATE ACQUIRED | H12: UNIT OF MEA. | I12: UNIT VALUE | J12: QTY PER PROP. CARD | K12: ACCOUNTABLE OFFICER | L12: LOCATION | M12: CONDITION | N12: QTY PER PHYSICAL COUNT | O12: SHORTAGE/ OVERAGE | Q12: REMARKS | R12: PHOTO LINK
O13: QTY | P13: VALUE
D15: OFFICE COMBI BLINDS | E15: 2018-NFA-002-FF-L-001 | H15: set | I15: 99971.58 | J15: 1 | K15: AMIELOU JANE G. MENDOZA | L15: Office Lobby | M15: Good Condition | N15: 1 | O15: 0 | P15: 0
D16: =UPPER("12 seater T-shape Conference Table") -> 12 SEATER T-SHAPE CONFERENCE TABLE | E16: 2022-NFA-00B-FF-D-001 | G16: 44208 | H16: set | I16: 97500 | J16: 1 | K16: AMIELOU JANE G. MENDOZA | L16: Conference Room | M16: Good Condition
F17: Sub Total | I17: =SUM(I15:I16) -> 197471.58
D26: Certified Correct by: | H26: Approved by: | M26: Verified by: | O26: Verified by:
D29: MARLON O. MARGALLO | H29: VERALEW DG. DE VERA
D30: Assistant Regional Manager | H30: Regional Manager II | M30: COA Representative | O30: COA Representative

Sheet AJ Mendoza.Final
Q1: Appendix 73
B2: NATIONAL FOOD AUTHORITY - CARAGA
B3: Regional Office No. XV
B4: As of Dec. 31, 2022
B6: REPORT ON THE PHYSICAL COUNT OF PROPERTY, PLANT AND EQUIPMENT
B8: Fund Cluster: __________
B9: For which, AMIELOU JANE G. MENDOZA - Acting SAO, NFA-Caraga Regional Office is accountable, having assumed such accountability on (________________).
B11: ARTICLE / ITEM | C11: Date Acquired | D11: DESCRIPTION | E11: PROPERTY NO. | F11: SERIAL NUMBER | G11: DATE ACQUIRED | H11: UNIT OF MEA. | I11: UNIT VALUE | J11: QTY PER PROP. CARD | K11: ACCOUNTABLE OFFICER | L11: LOCATION | M11: CONDITION | N11: QTY PER PHYSICAL COUNT | O11: SHORTAGE/ OVERAGE | Q11: REMARKS | R11: PHOTO LINK
O12: QTY | P12: VALUE
B13: BUILDING
C14: 43462 | D14: Building - Regional Office | E14: 2018-NFA-00B-BS-A-0028.5 | G14: 43462 | I14: 1782828.5 | J14: 1 | K14: AMIELOU JANE G. MENDOZA | L14: Libertad Compound, Bxu | M14: Good Condition | N14: 1 | O14: 0 | P14: 0 | R14: 1.jpg
C15: 28858 | D15: Building - Regional Office | E15: 1979-NFA-002-BS-A-001 | G15: 28915 | I15: 1476980.1 | J15: 1 | K15: AMIELOU JANE G. MENDOZA | L15: Libertad Compound, Bxu | M15: Good Condition | N15: 1 | O15: 0 | P15: 0
F16: Sub Total | I16: =SUM(I14:I15) -> 3259808.6
B17: COMMUNICATION EQUIPMENT
D18: Multimedia Projector, EPSON | E18: 2005-NFA-OOB-CM-G-002 | H18: pc | I18: 62994.75 | J18: 1 | K18: ROEL D. CAPERIG | L18: Common Storage Room ( Supply) | M18: Unserviceable | N18: 1 | O18: 0 | P18: 0 | Q18: IIRUP NO. CAR-IIR-2022-C-002
D19: Video Conferencing System TV SN:5204942, PC DELL - DJNY6K3, LOGITECH RALLY PLUS (TABLE HUB, DISPLAY HUB, CAMERA, MIC POS 1 & 2 SPEAKER L&R) | E19: 2022-NFA-MSD-CM-G-021 | G19: 44564 | H19: set | I19: 305103.38 | J19: 1 | K19: AMIELOU JANE G. MENDOZA | L19: Regional Office | M19: Good Condition | N19: 1 | O19: 0 | P19: 0
F20: Sub Total | I20: =SUM(I18:I19) -> 368098.13
B21: IT EQUIPMENT AND SOFTWARE
C22: 01/04/2007 | D22: SERVER, HP PROLIANT (UPGRADED) | E22: 2007-NFA-002-DP-F-001 | F22: ML350G4 | G22: 39086 | H22: pc. | I22: 244431.05 | J22: 1 | K22: ROEL D. CAPERIG | L22: Common Storage Room ( Supply) | M22: Unserviceable | N22: 1 | O22: 0 | P22: 0 | Q22: IIRUP NO. CAR-IIR-2022-C-001 | R22: 50.jpg
D23: B3-420 Notebook 14" Core15-1135g7 / 16B DDR4 / 512GB NVME PCI-E SSD, Intel IRIS XE Graphics, SN# JEXPM22325000059 | E23: 2022-NFA-MSD-DP-T-059 | F23: JEXPM22325000059 | G23: 44883 | H23: set | I23: 56400 | J23: 1 | K23: VERALEW DG. DE VERA | L23: RM's Office | M23: Good Condition | N23: 1 | O23: 0 | P23: 0
D24: CPU, HP Personal Computers | E24: 2005-NFA-OOB-DP-B-005 | G24: 38513 | H24: set | I24: 53665 | J24: 1 | K24: ROEL D. CAPERIG | L24: Common Storage Room ( Supply) | M24: Unserviceable | N24: 1 | O24: 0 | P24: 0 | Q24: IIRUP NO. CAR-IIR-2022-C-002
F25: Sub Total | I25: =SUM(I22:I24) -> 354496.05
B26: FURNITURE, FIXTURES & BOOKS
D27: OFFICE COMBI BLINDS | E27: 2018-NFA-002-FF-L-001 | H27: set | I27: 99971.58 | J27: 1 | K27: AMIELOU JANE G. MENDOZA | L27: Office Lobby | M27: Good Condition | N27: 1 | O27: 0 | P27: 0
D28: =UPPER("12 seater T-shape Conference Table") -> 12 SEATER T-SHAPE CONFERENCE TABLE | E28: 2022-NFA-00B-FF-D-001 | G28: 44208 | H28: set | I28: 97500 | J28: 1 | K28: AMIELOU JANE G. MENDOZA | L28: Conference Room | M28: Good Condition
F29: Sub Total | I29: =SUM(I27:I28) -> 197471.58
A30: 8 | B30: MOTOR VEHICLES, LAND TRANS. EQUIPT AND ACCESORIES
C31: 38737 | D31: TOYOTA INNOVA DSL MODEL 2005 ENGINE # 2KD-9547460 | E31: 2006-NFA-GSD-LT-C-132 | G31: 38737 | H31: unit | I31: 848000 | J31: 1 | K31: JESON JARIOL | L31: Regional Office | M31: Good Condition | N31: 1 | O31: 0 | P31: 0 | R31: 63.jpg
C32: 42636 | D32: ISUZU CROSSWIND SPORTIVO ENGINE # 4JA1M57459 CHASSIS # PABTBBR54FG2089995 | E32: 2016-NFA-GSD-LT-C-203 | G32: 42636 | H32: unit | I32: 1180000 | J32: 1 | K32: ALEXIS M. RAVELO | L32: Regional Office | M32: Good Condition | N32: 1 | O32: 0 | P32: 0 | R32: 64.jpg
D33: 2021 MITSUBISHI STRADA GLS 2.4D 2WD, 4N15UHC6103 SILVER METALIC, AT | E33: 2021-NFA-GSD-LT-C-229 | G33: 44439 | H33: unit | I33: 1397400 | J33: 1 | K33: JOJIT J. CASIO | L33: Regional Office | M33: Good Condition | N33: 1 | O33: 0 | P33: 0
F34: Sub Total | I34: =SUM(I31:I33) -> 3425400
B35: OFFICE EQUIPMENT | O35: 0 | P35: 0
C36: 01/11/2012 | D36: ROOM AIRCONDITIONER, SPLIT TYPE-WALL MOUNTED, 2.0 HP, W/ INVERTER , PANASONIC | E36: 2012-NFA-0B0-OE-C-010 | F36: 2486201743 | G36: 40919 | H36: set | I36: 55000 | J36: 1 | K36: LOVELLA MAY AWING | L36: Acctg. Section | M36: Good Condition | N36: 1 | O36: 0 | P36: 0 | R36: 71.jpg
C37: 41269 | D37: AIRCONDITIONER , PACKED TYPE-FLOOR MOUNTED , 3 TONS, KOPPEL | E37: 2012-NFA-0B0-OE-C-011 | F37: UE323210 | G37: 41269 | H37: set | I37: 81600 | J37: 1 | K37: AMIELOU JANE G. MENDOZA | L37: Office Lobby | M37: Good Condition | N37: 1 | O37: 0 | P37: 0 | R37: 72.jpg
C38: 41269 | D38: AIRCONDITIONER , PACKED TYPE-FLOOR MOUNTED , 3 TONS, KOPPEL | E38: 2012-NFA-0B0-OE-C-013 | F38: KE248331 | G38: 41269 | H38: set | I38: 81600 | J38: 1 | K38: AMIELOU JANE G. MENDOZA | L38: Office Lobby | M38: Good Condition | N38: 1 | O38: 0 | P38: 0 | R38: 74.jpg
C39: 42718 | D39: CHILLER, 2 DOOR SHOWCASE TYPE, CAPACITY 1,000 LTRS | E39: 2016-NFA-00B-OE-T-003 | G39: 42718 | H39: set | I39: 68000 | J39: 1 | K39: GERLIZA L. MULA | L39: TRSD Section | M39: Good Condition | N39: 1 | O39: 0 | P39: 0 | R39: 87.jpg
D40: KOPPEL 3.0 TR FLOOR MOUNTED INVERTER | E40: 2022-NFA-00B-OE-C-020 | G40: 44656 | H40: set | I40: 106000 | J40: 1 | K40: AMIELOU JANE G. MENDOZA | L40: Old RO Office | M40: Good Condition | N40: 1
F41: Sub Total | I41: =SUM(I36:I40) -> 392200
B42: TECHNICAL & SCIENTIFIC EQUIPMENT EQUIPMENT
C43: 08/23/2006 | D43: OHAUS ANALYTICAL BALANCE ADVENTURE 210G X 0.1 MODEL :AR 2140 | E43: 2006-NFA-00B-TS-D-001 | F43: 1227070326 | G43: 38952 | H43: pc. | I43: 80590 | J43: 1 | K43: GERLIZA L. MULA | L43: TRSD Section | M43: Good Condition | N43: 1 | O43: 0 | P43: 0 | R43: 93.jpg
C44: 09/27/2007 | D44: OVEN LABORATORY FOR DRYING BINDER BRAND, GERMANY MODEL;ED 53 | E44: 2007-NFA-TRD-TS-D-315 | F44: 07-17295 | G44: 39352 | H44: pc. | I44: 55000 | J44: 1 | K44: GERLIZA L. MULA | L44: TRSD Section | M44: Good Condition | N44: 1 | O44: 0 | P44: 0 | R44: 100.jpg
C45: 02/21/2011 | D45: LABORATORY SAMPLE GRINDER ROMER MILL SERIES W/ ACCESSORIES | E45: 2011-NFA-TRD-TS-D-1163 | F45: 10050233 | G45: 40595 | H45: pc. | I45: 299500 | J45: 1 | K45: GERLIZA L. MULA | L45: TRSD Section | M45: Good Condition | N45: 1 | O45: 0 | P45: 0 | R45: 97.jpg
C46: 05/02/2017 | D46: ANALYTICAL BALANCE CAPACITY 220G X 0.1MG (BRAND: OHAUS) | E46: 2017-NFA-TRS-TS-D-703 | G46: 42857 | H46: pc. | I46: 63930 | J46: 1 | K46: GERLIZA L. MULA | L46: TRSD Section | M46: Good Condition | N46: 1 | O46: 0 | P46: 0 | R46: 101.jpg
C47: 41591 | D47: LABORATORY POLISHING MACHINE W/ BASIC TOOLS ACCESSORIES | E47: 2013-NFA-TRS-TS-P-008 | F47: S6704/29 | G47: 41591 | H47: set | I47: 248000 | J47: 1 | K47: GERLIZA L. MULA | L47: TRSD Section | M47: Good Condition | N47: 1 | O47: 0 | P47: 0 | R47: 104.jpg
C48: 8/13/2021 | D48: LABORATORY POLISHING MACHINE | E48: 2021-NFA-OCD-TS-P-025 | F48: G2003053 | G48: 44421 | H48: set | I48: 471744 | J48: 1 | K48: GERLIZA L. MULA | L48: TRSD Section | M48: Good Condition | N48: 1 | O48: 0 | P48: 0
C49: 11/24/2021 | D49: LABORATORY HULLER | E49: 2021-NFA-TRS-TS-D-1221 | F49: CB00406 | G49: 44524 | H49: set | I49: 285600 | J49: 1 | K49: GERLIZA L. MULA | L49: TRSD Section | M49: Good Condition | N49: 1 | O49: 0 | P49: 0
F50: Sub Total | I50: =SUM(I43:I49) -> 1504364
B51: PLANT MACHINERY & EQUIPMENT
C52: 1/24/2011 | D52: Generator Set Kubota | E52: 2013-NFA-00B-PE-V-002 | H52: set | I52: 439700 | J52: 1 | K52: ROBERT BACANGGOY | L52: GenSet House | M52: Needing Repair | N52: 1 | O52: 0 | P52: 0
F53: Sub Total | I53: =SUM(I52:I52) -> 439700
D56: Certified Correct by: | H56: Approved by: | M56: Verified by: | O56: Verified by:
D59: MARLON O. MARGALLO | H59: VERALEW DG. DE VERA
D60: Assistant Regional Manager | H60: Regional Manager II | M60: COA Representative | O60: COA Representative

Sheet G Mula
Q1: Appendix 73
B2: NATIONAL FOOD AUTHORITY - CARAGA
B3: Regional Office No. XV
B4: As of Dec. 31, 2022
B6: REPORT ON THE PHYSICAL COUNT OF PROPERTY, PLANT AND EQUIPMENT
B8: Fund Cluster: __________
B9: For which, GERLIZA L. MULA - RSQAO, NFA-Caraga Regional Office is accountable, having assumed such accountability on (________________).
B11: ARTICLE / ITEM | C11: Date Acquired | D11: DESCRIPTION | E11: PROPERTY NO. | F11: SERIAL NUMBER | G11: DATE ACQUIRED | H11: UNIT OF MEA. | I11: UNIT VALUE | J11: QTY PER PROP. CARD | K11: ACCOUNTABLE OFFICER | L11: LOCATION | M11: CONDITION | N11: QTY PER PHYSICAL COUNT | O11: SHORTAGE/ OVERAGE | Q11: REMARKS | R11: PHOTO LINK
O12: QTY | P12: VALUE
B13: BUILDING
C14: 43462 | D14: Building - Regional Office | E14: 2018-NFA-00B-BS-A-0028.5 | G14: 43462 | I14: 1782828.5 | J14: 1 | K14: AMIELOU JANE G. MENDOZA | L14: Libertad Compound, Bxu | M14: Good Condition | N14: 1 | O14: 0 | P14: 0 | R14: 1.jpg
C15: 28858 | D15: Building - Regional Office | E15: 1979-NFA-002-BS-A-001 | G15: 28915 | I15: 1476980.1 | J15: 1 | K15: AMIELOU JANE G. MENDOZA | L15: Libertad Compound, Bxu | M15: Good Condition | N15: 1 | O15: 0 | P15: 0
F16: Sub Total | I16: =SUM(I14:I15) -> 3259808.6
B17: COMMUNICATION EQUIPMENT
D18: Multimedia Projector, EPSON | E18: 2005-NFA-OOB-CM-G-002 | H18: pc | I18: 62994.75 | J18: 1 | K18: ROEL D. CAPERIG | L18: Common Storage Room ( Supply) | M18: Unserviceable | N18: 1 | O18: 0 | P18: 0 | Q18: IIRUP NO. CAR-IIR-2022-C-002
D19: Video Conferencing System TV SN:5204942, PC DELL - DJNY6K3, LOGITECH RALLY PLUS (TABLE HUB, DISPLAY HUB, CAMERA, MIC POS 1 & 2 SPEAKER L&R) | E19: 2022-NFA-MSD-CM-G-021 | G19: 44564 | H19: set | I19: 305103.38 | J19: 1 | K19: AMIELOU JANE G. MENDOZA | L19: Regional Office | M19: Good Condition | N19: 1 | O19: 0 | P19: 0
F20: Sub Total | I20: =SUM(I18:I19) -> 368098.13
B21: IT EQUIPMENT AND SOFTWARE
C22: 01/04/2007 | D22: SERVER, HP PROLIANT (UPGRADED) | E22: 2007-NFA-002-DP-F-001 | F22: ML350G4 | G22: 39086 | H22: pc. | I22: 244431.05 | J22: 1 | K22: ROEL D. CAPERIG | L22: Common Storage Room ( Supply) | M22: Unserviceable | N22: 1 | O22: 0 | P22: 0 | Q22: IIRUP NO. CAR-IIR-2022-C-001 | R22: 50.jpg
D23: B3-420 Notebook 14" Core15-1135g7 / 16B DDR4 / 512GB NVME PCI-E SSD, Intel IRIS XE Graphics, SN# JEXPM22325000059 | E23: 2022-NFA-MSD-DP-T-059 | F23: JEXPM22325000059 | G23: 44883 | H23: set | I23: 56400 | J23: 1 | K23: VERALEW DG. DE VERA | L23: RM's Office | M23: Good Condition | N23: 1 | O23: 0 | P23: 0
D24: CPU, HP Personal Computers | E24: 2005-NFA-OOB-DP-B-005 | G24: 38513 | H24: set | I24: 53665 | J24: 1 | K24: ROEL D. CAPERIG | L24: Common Storage Room ( Supply) | M24: Unserviceable | N24: 1 | O24: 0 | P24: 0 | Q24: IIRUP NO. CAR-IIR-2022-C-002
F25: Sub Total | I25: =SUM(I22:I24) -> 354496.05
B26: FURNITURE, FIXTURES & BOOKS
D27: OFFICE COMBI BLINDS | E27: 2018-NFA-002-FF-L-001 | H27: set | I27: 99971.58 | J27: 1 | K27: AMIELOU JANE G. MENDOZA | L27: Office Lobby | M27: Good Condition | N27: 1 | O27: 0 | P27: 0
D28: =UPPER("12 seater T-shape Conference Table") -> 12 SEATER T-SHAPE CONFERENCE TABLE | E28: 2022-NFA-00B-FF-D-001 | G28: 44208 | H28: set | I28: 97500 | J28: 1 | K28: AMIELOU JANE G. MENDOZA | L28: Conference Room | M28: Good Condition
F29: Sub Total | I29: =SUM(I27:I28) -> 197471.58
A30: 8 | B30: MOTOR VEHICLES, LAND TRANS. EQUIPT AND ACCESORIES
C31: 38737 | D31: TOYOTA INNOVA DSL MODEL 2005 ENGINE # 2KD-9547460 | E31: 2006-NFA-GSD-LT-C-132 | G31: 38737 | H31: unit | I31: 848000 | J31: 1 | K31: JESON JARIOL | L31: Regional Office | M31: Good Condition | N31: 1 | O31: 0 | P31: 0 | R31: 63.jpg
C32: 42636 | D32: ISUZU CROSSWIND SPORTIVO ENGINE # 4JA1M57459 CHASSIS # PABTBBR54FG2089995 | E32: 2016-NFA-GSD-LT-C-203 | G32: 42636 | H32: unit | I32: 1180000 | J32: 1 | K32: ALEXIS M. RAVELO | L32: Regional Office | M32: Good Condition | N32: 1 | O32: 0 | P32: 0 | R32: 64.jpg
D33: 2021 MITSUBISHI STRADA GLS 2.4D 2WD, 4N15UHC6103 SILVER METALIC, AT | E33: 2021-NFA-GSD-LT-C-229 | G33: 44439 | H33: unit | I33: 1397400 | J33: 1 | K33: JOJIT J. CASIO | L33: Regional Office | M33: Good Condition | N33: 1 | O33: 0 | P33: 0
F34: Sub Total | I34: =SUM(I31:I33) -> 3425400
B35: OFFICE EQUIPMENT | O35: 0 | P35: 0
C36: 01/11/2012 | D36: ROOM AIRCONDITIONER, SPLIT TYPE-WALL MOUNTED, 2.0 HP, W/ INVERTER , PANASONIC | E36: 2012-NFA-0B0-OE-C-010 | F36: 2486201743 | G36: 40919 | H36: set | I36: 55000 | J36: 1 | K36: LOVELLA MAY AWING | L36: Acctg. Section | M36: Good Condition | N36: 1 | O36: 0 | P36: 0 | R36: 71.jpg
C37: 41269 | D37: AIRCONDITIONER , PACKED TYPE-FLOOR MOUNTED , 3 TONS, KOPPEL | E37: 2012-NFA-0B0-OE-C-011 | F37: UE323210 | G37: 41269 | H37: set | I37: 81600 | J37: 1 | K37: AMIELOU JANE G. MENDOZA | L37: Office Lobby | M37: Good Condition | N37: 1 | O37: 0 | P37: 0 | R37: 72.jpg
C38: 41269 | D38: AIRCONDITIONER , PACKED TYPE-FLOOR MOUNTED , 3 TONS, KOPPEL | E38: 2012-NFA-0B0-OE-C-013 | F38: KE248331 | G38: 41269 | H38: set | I38: 81600 | J38: 1 | K38: AMIELOU JANE G. MENDOZA | L38: Office Lobby | M38: Good Condition | N38: 1 | O38: 0 | P38: 0 | R38: 74.jpg
C39: 42718 | D39: CHILLER, 2 DOOR SHOWCASE TYPE, CAPACITY 1,000 LTRS | E39: 2016-NFA-00B-OE-T-003 | G39: 42718 | H39: set | I39: 68000 | J39: 1 | K39: GERLIZA L. MULA | L39: TRSD Section | M39: Good Condition | N39: 1 | O39: 0 | P39: 0 | R39: 87.jpg
D40: KOPPEL 3.0 TR FLOOR MOUNTED INVERTER | E40: 2022-NFA-00B-OE-C-020 | G40: 44656 | H40: set | I40: 106000 | J40: 1 | K40: AMIELOU JANE G. MENDOZA | L40: Old RO Office | M40: Good Condition | N40: 1
F41: Sub Total | I41: =SUM(I36:I40) -> 392200
B42: TECHNICAL & SCIENTIFIC EQUIPMENT EQUIPMENT
C43: 08/23/2006 | D43: OHAUS ANALYTICAL BALANCE ADVENTURE 210G X 0.1 MODEL :AR 2140 | E43: 2006-NFA-00B-TS-D-001 | F43: 1227070326 | G43: 38952 | H43: pc. | I43: 80590 | J43: 1 | K43: GERLIZA L. MULA | L43: TRSD Section | M43: Good Condition | N43: 1 | O43: 0 | P43: 0 | R43: 93.jpg
C44: 09/27/2007 | D44: OVEN LABORATORY FOR DRYING BINDER BRAND, GERMANY MODEL;ED 53 | E44: 2007-NFA-TRD-TS-D-315 | F44: 07-17295 | G44: 39352 | H44: pc. | I44: 55000 | J44: 1 | K44: GERLIZA L. MULA | L44: TRSD Section | M44: Good Condition | N44: 1 | O44: 0 | P44: 0 | R44: 100.jpg
C45: 02/21/2011 | D45: LABORATORY SAMPLE GRINDER ROMER MILL SERIES W/ ACCESSORIES | E45: 2011-NFA-TRD-TS-D-1163 | F45: 10050233 | G45: 40595 | H45: pc. | I45: 299500 | J45: 1 | K45: GERLIZA L. MULA | L45: TRSD Section | M45: Good Condition | N45: 1 | O45: 0 | P45: 0 | R45: 97.jpg
C46: 05/02/2017 | D46: ANALYTICAL BALANCE CAPACITY 220G X 0.1MG (BRAND: OHAUS) | E46: 2017-NFA-TRS-TS-D-703 | G46: 42857 | H46: pc. | I46: 63930 | J46: 1 | K46: GERLIZA L. MULA | L46: TRSD Section | M46: Good Condition | N46: 1 | O46: 0 | P46: 0 | R46: 101.jpg
C47: 41591 | D47: LABORATORY POLISHING MACHINE W/ BASIC TOOLS ACCESSORIES | E47: 2013-NFA-TRS-TS-P-008 | F47: S6704/29 | G47: 41591 | H47: set | I47: 248000 | J47: 1 | K47: GERLIZA L. MULA | L47: TRSD Section | M47: Good Condition | N47: 1 | O47: 0 | P47: 0 | R47: 104.jpg
C48: 8/13/2021 | D48: LABORATORY POLISHING MACHINE | E48: 2021-NFA-OCD-TS-P-025 | F48: G2003053 | G48: 44421 | H48: set | I48: 471744 | J48: 1 | K48: GERLIZA L. MULA | L48: TRSD Section | M48: Good Condition | N48: 1 | O48: 0 | P48: 0
C49: 11/24/2021 | D49: LABORATORY HULLER | E49: 2021-NFA-TRS-TS-D-1221 | F49: CB00406 | G49: 44524 | H49: set | I49: 285600 | J49: 1 | K49: GERLIZA L. MULA | L49: TRSD Section | M49: Good Condition | N49: 1 | O49: 0 | P49: 0
F50: Sub Total | I50: =SUM(I43:I49) -> 1504364
B51: PLANT MACHINERY & EQUIPMENT
C52: 1/24/2011 | D52: Generator Set Kubota | E52: 2013-NFA-00B-PE-V-002 | H52: set | I52: 439700 | J52: 1 | K52: ROBERT BACANGGOY | L52: GenSet House | M52: Needing Repair | N52: 1 | O52: 0 | P52: 0
F53: Sub Total | I53: =SUM(I52:I52) -> 439700
I54: =+I16+I20+I25+I29+I34+I41+I50+I53 -> 9941538.3
D56: Certified Correct by: | H56: Approved by: | M56: Verified by: | O56: Verified by:
D59: MARLON O. MARGALLO | H59: VERALEW DG. DE VERA
D60: Assistant Regional Manager | H60: Regional Manager II | M60: COA Representative | O60: COA Representative

Sheet R. Bacanggoy
Q1: Appendix 73
B2: NATIONAL FOOD AUTHORITY - CARAGA
B3: Regional Office No. XV
B4: As of Dec. 31, 2022
B6: REPORT ON THE PHYSICAL COUNT OF PROPERTY, PLANT AND EQUIPMENT
B9: Fund Cluster: __________
B10: For which, ROBERT BACANGGOY - Engineer III, NFA-Caraga Regional Office is accountable, having assumed such accountability on (________________).
B12: ARTICLE / ITEM | C12: Date Acquired | D12: DESCRIPTION | E12: PROPERTY NO. | F12: SERIAL NUMBER | G12: DATE ACQUIRED | H12: UNIT OF MEA. | I12: UNIT VALUE | J12: QTY PER PROP. CARD | K12: ACCOUNTABLE OFFICER | L12: LOCATION | M12: CONDITION | N12: QTY PER PHYSICAL COUNT | O12: SHORTAGE/ OVERAGE | Q12: REMARKS | R12: PHOTO LINK
O13: QTY | P13: VALUE
B14: PLANT MACHINERY & EQUIPMENT
C15: 1/24/2011 | D15: Generator Set Kubota | E15: 2013-NFA-00B-PE-V-002 | H15: set | I15: 439700 | J15: 1 | K15: ROBERT BACANGGOY | L15: GenSet House | M15: Needing Repair | N15: 1 | O15: 0 | P15: 0
F24: Sub Total
D27: Certified Correct by: | H27: Approved by: | M27: Verified by: | O27: Verified by:
D30: MARLON O. MARGALLO | H30: VERALEW DG. DE VERA
D31: Assistant Regional Manager | H31: Regional Manager II | M31: COA Representative | O31: COA Representative

Sheet V De Vera
Q1: Appendix 73
B2: NATIONAL FOOD AUTHORITY - CARAGA
B3: Regional Office No. XV
B4: As of Dec. 31, 2022
B6: REPORT ON THE PHYSICAL COUNT OF PROPERTY, PLANT AND EQUIPMENT
B9: Fund Cluster: __________
B10: For which, VERALEW DG. DE VERA - Regional Manager II, NFA-Caraga Regional Office is accountable, having assumed such accountability on (________________).
B12: ARTICLE / ITEM | C12: Date Acquired | D12: DESCRIPTION | E12: PROPERTY NO. | F12: SERIAL NUMBER | G12: DATE ACQUIRED | H12: UNIT OF MEA. | I12: UNIT VALUE | J12: QTY PER PROP. CARD | K12: ACCOUNTABLE OFFICER | L12: LOCATION | M12: CONDITION | N12: QTY PER PHYSICAL COUNT | O12: SHORTAGE/ OVERAGE | Q12: REMARKS | R12: PHOTO LINK
O13: QTY | P13: VALUE
B14: BUILDING
C15: 43462 | D15: Building - Regional Office | E15: 2018-NFA-00B-BS-A-0028.5 | G15: 43462 | I15: 1782828.5 | J15: 1 | K15: AMIELOU JANE G. MENDOZA | L15: Libertad Compound, Bxu | M15: Good Condition | N15: 1 | O15: 0 | P15: 0 | R15: 1.jpg
C16: 28858 | D16: Building - Regional Office | E16: 1979-NFA-002-BS-A-001 | G16: 28915 | I16: 1476980.1 | J16: 1 | K16: AMIELOU JANE G. MENDOZA | L16: Libertad Compound, Bxu | M16: Good Condition | N16: 1 | O16: 0 | P16: 0
F17: Sub Total | I17: =SUM(I15:I16) -> 3259808.6
B18: COMMUNICATION EQUIPMENT
D19: Multimedia Projector, EPSON | E19: 2005-NFA-OOB-CM-G-002 | H19: pc | I19: 62994.75 | J19: 1 | K19: ROEL D. CAPERIG | L19: Common Storage Room ( Supply) | M19: Unserviceable | N19: 1 | O19: 0 | P19: 0 | Q19: IIRUP NO. CAR-IIR-2022-C-002
D20: Video Conferencing System TV SN:5204942, PC DELL - DJNY6K3, LOGITECH RALLY PLUS (TABLE HUB, DISPLAY HUB, CAMERA, MIC POS 1 & 2 SPEAKER L&R) | E20: 2022-NFA-MSD-CM-G-021 | G20: 44564 | H20: set | I20: 305103.38 | J20: 1 | K20: AMIELOU JANE G. MENDOZA | L20: Regional Office | M20: Good Condition | N20: 1 | O20: 0 | P20: 0
F21: Sub Total | I21: =SUM(I19:I20) -> 368098.13
B22: IT EQUIPMENT AND SOFTWARE
C23: 01/04/2007 | D23: SERVER, HP PROLIANT (UPGRADED) | E23: 2007-NFA-002-DP-F-001 | F23: ML350G4 | G23: 39086 | H23: pc. | I23: 244431.05 | J23: 1 | K23: ROEL D. CAPERIG | L23: Common Storage Room ( Supply) | M23: Unserviceable | N23: 1 | O23: 0 | P23: 0 | Q23: IIRUP NO. CAR-IIR-2022-C-001 | R23: 50.jpg
D24: B3-420 Notebook 14" Core15-1135g7 / 16B DDR4 / 512GB NVME PCI-E SSD, Intel IRIS XE Graphics, SN# JEXPM22325000059 | E24: 2022-NFA-MSD-DP-T-059 | F24: JEXPM22325000059 | G24: 44883 | H24: set | I24: 56400 | J24: 1 | K24: VERALEW DG. DE VERA | L24: RM's Office | M24: Good Condition | N24: 1 | O24: 0 | P24: 0
D25: CPU, HP Personal Computers | E25: 2005-NFA-OOB-DP-B-005 | G25: 38513 | H25: set | I25: 53665 | J25: 1 | K25: ROEL D. CAPERIG | L25: Common Storage Room ( Supply) | M25: Unserviceable | N25: 1 | O25: 0 | P25: 0 | Q25: IIRUP NO. CAR-IIR-2022-C-002
F26: Sub Total | I26: =SUM(I23:I25) -> 354496.05
B27: FURNITURE, FIXTURES & BOOKS
D28: OFFICE COMBI BLINDS | E28: 2018-NFA-002-FF-L-001 | H28: set | I28: 99971.58 | J28: 1 | K28: AMIELOU JANE G. MENDOZA | L28: Office Lobby | M28: Good Condition | N28: 1 | O28: 0 | P28: 0
D29: =UPPER("12 seater T-shape Conference Table") -> 12 SEATER T-SHAPE CONFERENCE TABLE | E29: 2022-NFA-00B-FF-D-001 | G29: 44208 | H29: set | I29: 97500 | J29: 1 | K29: AMIELOU JANE G. MENDOZA | L29: Conference Room | M29: Good Condition
F30: Sub Total | I30: =SUM(I28:I29) -> 197471.58
A31: 8 | B31: MOTOR VEHICLES, LAND TRANS. EQUIPT AND ACCESORIES
C32: 38737 | D32: TOYOTA INNOVA DSL MODEL 2005 ENGINE # 2KD-9547460 | E32: 2006-NFA-GSD-LT-C-132 | G32: 38737 | H32: unit | I32: 848000 | J32: 1 | K32: JESON JARIOL | L32: Regional Office | M32: Good Condition | N32: 1 | O32: 0 | P32: 0 | R32: 63.jpg
C33: 42636 | D33: ISUZU CROSSWIND SPORTIVO ENGINE # 4JA1M57459 CHASSIS # PABTBBR54FG2089995 | E33: 2016-NFA-GSD-LT-C-203 | G33: 42636 | H33: unit | I33: 1180000 | J33: 1 | K33: ALEXIS M. RAVELO | L33: Regional Office | M33: Good Condition | N33: 1 | O33: 0 | P33: 0 | R33: 64.jpg
D34: 2021 MITSUBISHI STRADA GLS 2.4D 2WD, 4N15UHC6103 SILVER METALIC, AT | E34: 2021-NFA-GSD-LT-C-229 | G34: 44439 | H34: unit | I34: 1397400 | J34: 1 | K34: JOJIT J. CASIO | L34: Regional Office | M34: Good Condition | N34: 1 | O34: 0 | P34: 0
F35: Sub Total | I35: =SUM(I32:I34) -> 3425400
B36: OFFICE EQUIPMENT | O36: 0 | P36: 0
C37: 01/11/2012 | D37: ROOM AIRCONDITIONER, SPLIT TYPE-WALL MOUNTED, 2.0 HP, W/ INVERTER , PANASONIC | E37: 2012-NFA-0B0-OE-C-010 | F37: 2486201743 | G37: 40919 | H37: set | I37: 55000 | J37: 1 | K37: LOVELLA MAY AWING | L37: Acctg. Section | M37: Good Condition | N37: 1 | O37: 0 | P37: 0 | R37: 71.jpg
C38: 41269 | D38: AIRCONDITIONER , PACKED TYPE-FLOOR MOUNTED , 3 TONS, KOPPEL | E38: 2012-NFA-0B0-OE-C-011 | F38: UE323210 | G38: 41269 | H38: set | I38: 81600 | J38: 1 | K38: AMIELOU JANE G. MENDOZA | L38: Office Lobby | M38: Good Condition | N38: 1 | O38: 0 | P38: 0 | R38: 72.jpg
C39: 41269 | D39: AIRCONDITIONER , PACKED TYPE-FLOOR MOUNTED , 3 TONS, KOPPEL | E39: 2012-NFA-0B0-OE-C-013 | F39: KE248331 | G39: 41269 | H39: set | I39: 81600 | J39: 1 | K39: AMIELOU JANE G. MENDOZA | L39: Office Lobby | M39: Good Condition | N39: 1 | O39: 0 | P39: 0 | R39: 74.jpg
C40: 42718 | D40: CHILLER, 2 DOOR SHOWCASE TYPE, CAPACITY 1,000 LTRS | E40: 2016-NFA-00B-OE-T-003 | G40: 42718 | H40: set | I40: 68000 | J40: 1 | K40: GERLIZA L. MULA | L40: TRSD Section | M40: Good Condition | N40: 1 | O40: 0 | P40: 0 | R40: 87.jpg
D41: KOPPEL 3.0 TR FLOOR MOUNTED INVERTER | E41: 2022-NFA-00B-OE-C-020 | G41: 44656 | H41: set | I41: 106000 | J41: 1 | K41: AMIELOU JANE G. MENDOZA | L41: Old RO Office | M41: Good Condition | N41: 1
F42: Sub Total | I42: =SUM(I37:I41) -> 392200
B43: TECHNICAL & SCIENTIFIC EQUIPMENT EQUIPMENT
C44: 08/23/2006 | D44: OHAUS ANALYTICAL BALANCE ADVENTURE 210G X 0.1 MODEL :AR 2140 | E44: 2006-NFA-00B-TS-D-001 | F44: 1227070326 | G44: 38952 | H44: pc. | I44: 80590 | J44: 1 | K44: GERLIZA L. MULA | L44: TRSD Section | M44: Good Condition | N44: 1 | O44: 0 | P44: 0 | R44: 93.jpg
C45: 09/27/2007 | D45: OVEN LABORATORY FOR DRYING BINDER BRAND, GERMANY MODEL;ED 53 | E45: 2007-NFA-TRD-TS-D-315 | F45: 07-17295 | G45: 39352 | H45: pc. | I45: 55000 | J45: 1 | K45: GERLIZA L. MULA | L45: TRSD Section | M45: Good Condition | N45: 1 | O45: 0 | P45: 0 | R45: 100.jpg
C46: 02/21/2011 | D46: LABORATORY SAMPLE GRINDER ROMER MILL SERIES W/ ACCESSORIES | E46: 2011-NFA-TRD-TS-D-1163 | F46: 10050233 | G46: 40595 | H46: pc. | I46: 299500 | J46: 1 | K46: GERLIZA L. MULA | L46: TRSD Section | M46: Good Condition | N46: 1 | O46: 0 | P46: 0 | R46: 97.jpg
C47: 05/02/2017 | D47: ANALYTICAL BALANCE CAPACITY 220G X 0.1MG (BRAND: OHAUS) | E47: 2017-NFA-TRS-TS-D-703 | G47: 42857 | H47: pc. | I47: 63930 | J47: 1 | K47: GERLIZA L. MULA | L47: TRSD Section | M47: Good Condition | N47: 1 | O47: 0 | P47: 0 | R47: 101.jpg
C48: 41591 | D48: LABORATORY POLISHING MACHINE W/ BASIC TOOLS ACCESSORIES | E48: 2013-NFA-TRS-TS-P-008 | F48: S6704/29 | G48: 41591 | H48: set | I48: 248000 | J48: 1 | K48: GERLIZA L. MULA | L48: TRSD Section | M48: Good Condition | N48: 1 | O48: 0 | P48: 0 | R48: 104.jpg
D57: Certified Correct by: | H57: Approved by: | M57: Verified by: | O57: Verified by:
D60: MARLON O. MARGALLO | H60: VERALEW DG. DE VERA
D61: Assistant Regional Manager | H61: Regional Manager II | M61: COA Representative | O61: COA Representative

Sheet R. Caperig
Q1: Appendix 73
B2: NATIONAL FOOD AUTHORITY - CARAGA
B3: Regional Office No. XV
B4: As of Dec. 31, 2022
B6: REPORT ON THE PHYSICAL COUNT OF PROPERTY, PLANT AND EQUIPMENT
B9: Fund Cluster: __________
B10: For which, ROEL D. CAPERIG - PMO, NFA-Caraga Regional Office is accountable, having assumed such accountability on (________________).
B12: ARTICLE / ITEM | C12: Date Acquired | D12: DESCRIPTION | E12: PROPERTY NO. | F12: SERIAL NUMBER | G12: DATE ACQUIRED | H12: UNIT OF MEA. | I12: UNIT VALUE | J12: QTY PER PROP. CARD | K12: ACCOUNTABLE OFFICER | L12: LOCATION | M12: CONDITION | N12: QTY PER PHYSICAL COUNT | O12: SHORTAGE/ OVERAGE | Q12: REMARKS | R12: PHOTO LINK
O13: QTY | P13: VALUE
B14: COMMUNICATION EQUIPMENT
D15: Multimedia Projector, EPSON | E15: 2005-NFA-OOB-CM-G-002 | H15: pc | I15: 62994.75 | J15: 1 | K15: ROEL D. CAPERIG | L15: Common Storage Room ( Supply) | M15: Unserviceable | N15: 1 | O15: 0 | P15: 0 | Q15: IIRUP NO. CAR-IIR-2022-C-002
B16: IT EQUIPMENT AND SOFTWARE
C17: 01/04/2007 | D17: SERVER, HP PROLIANT (UPGRADED) | E17: 2007-NFA-002-DP-F-001 | F17: ML350G4 | G17: 39086 | H17: pc. | I17: 244431.05 | J17: 1 | K17: ROEL D. CAPERIG | L17: Common Storage Room ( Supply) | M17: Unserviceable | N17: 1 | O17: 0 | P17: 0 | Q17: IIRUP NO. CAR-IIR-2022-C-001 | R17: 50.jpg
D18: CPU, HP Personal Computers | E18: 2005-NFA-OOB-DP-B-005 | G18: 38513 | H18: set | I18: 53665 | J18: 1 | K18: ROEL D. CAPERIG | L18: Common Storage Room ( Supply) | M18: Unserviceable | N18: 1 | O18: 0 | P18: 0 | Q18: IIRUP NO. CAR-IIR-2022-C-002
D26: Certified Correct by: | H26: Approved by: | M26: Verified by: | O26: Verified by:
D29: MARLON O. MARGALLO | H29: VERALEW DG. DE VERA
D30: Assistant Regional Manager | H30: Regional Manager II | M30: COA Representative | O30: COA Representative

Sheet L. Awing
Q1: Appendix 73
B2: NATIONAL FOOD AUTHORITY - CARAGA
B3: Regional Office No. XV
B4: As of Dec. 31, 2022
B6: REPORT ON THE PHYSICAL COUNT OF PROPERTY, PLANT AND EQUIPMENT
B9: Fund Cluster: __________
B10: For which, LOVELLA MAY AWING - Acting Accountant IV, NFA-Caraga Regional Office is accountable, having assumed such accountability on (________________).
B12: ARTICLE / ITEM | C12: Date Acquired | D12: DESCRIPTION | E12: PROPERTY NO. | F12: SERIAL NUMBER | G12: DATE ACQUIRED | H12: UNIT OF MEA. | I12: UNIT VALUE | J12: QTY PER PROP. CARD | K12: ACCOUNTABLE OFFICER | L12: LOCATION | M12: CONDITION | N12: QTY PER PHYSICAL COUNT | O12: SHORTAGE/ OVERAGE | Q12: REMARKS | R12: PHOTO LINK
O13: QTY | P13: VALUE
B14: OFFICE EQUIPMENT | O14: 0 | P14: 0
C15: 01/11/2012 | D15: ROOM AIRCONDITIONER, SPLIT TYPE-WALL MOUNTED, 2.0 HP, W/ INVERTER , PANASONIC | E15: 2012-NFA-0B0-OE-C-010 | F15: 2486201743 | G15: 40919 | H15: set | I15: 55000 | J15: 1 | K15: LOVELLA MAY AWING | L15: Acctg. Section | M15: Good Condition | N15: 1 | O15: 0 | P15: 0 | R15: 71.jpg
D27: Certified Correct by: | H27: Approved by: | M27: Verified by: | O27: Verified by:
D30: MARLON O. MARGALLO | H30: VERALEW DG. DE VERA
D31: Assistant Regional Manager | H31: Regional Manager II | M31: COA Representative | O31: COA Representative

Sheet J. Jariol
Q1: Appendix 73
B2: NATIONAL FOOD AUTHORITY - CARAGA
B3: Regional Office No. XV
B4: As of Dec. 31, 2022
B6: REPORT ON THE PHYSICAL COUNT OF PROPERTY, PLANT AND EQUIPMENT
B9: Fund Cluster: __________
B10: For which, ROEL D. CAPERIG - PMO, NFA-Caraga Regional Office is accountable, having assumed such accountability on (________________).
B12: ARTICLE / ITEM | C12: Date Acquired | D12: DESCRIPTION | E12: PROPERTY NO. | F12: SERIAL NUMBER | G12: DATE ACQUIRED | H12: UNIT OF MEA. | I12: UNIT VALUE | J12: QTY PER PROP. CARD | K12: ACCOUNTABLE OFFICER | L12: LOCATION | M12: CONDITION | N12: QTY PER PHYSICAL COUNT | O12: SHORTAGE/ OVERAGE | Q12: REMARKS | R12: PHOTO LINK
O13: QTY | P13: VALUE
B14: BUILDING
C15: 43462 | D15: Building - Regional Office | E15: 2018-NFA-00B-BS-A-0028.5 | G15: 43462 | I15: 1782828.5 | J15: 1 | K15: AMIELOU JANE G. MENDOZA | L15: Libertad Compound, Bxu | M15: Good Condition | N15: 1 | O15: 0 | P15: 0 | R15: 1.jpg
C16: 28858 | D16: Building - Regional Office | E16: 1979-NFA-002-BS-A-001 | G16: 28915 | I16: 1476980.1 | J16: 1 | K16: AMIELOU JANE G. MENDOZA | L16: Libertad Compound, Bxu | M16: Good Condition | N16: 1 | O16: 0 | P16: 0
F17: Sub Total | I17: =SUM(I15:I16) -> 3259808.6
B18: COMMUNICATION EQUIPMENT
D19: Multimedia Projector, EPSON | E19: 2005-NFA-OOB-CM-G-002 | H19: pc | I19: 62994.75 | J19: 1 | K19: ROEL D. CAPERIG | L19: Common Storage Room ( Supply) | M19: Unserviceable | N19: 1 | O19: 0 | P19: 0 | Q19: IIRUP NO. CAR-IIR-2022-C-002
D20: Video Conferencing System TV SN:5204942, PC DELL - DJNY6K3, LOGITECH RALLY PLUS (TABLE HUB, DISPLAY HUB, CAMERA, MIC POS 1 & 2 SPEAKER L&R) | E20: 2022-NFA-MSD-CM-G-021 | G20: 44564 | H20: set | I20: 305103.38 | J20: 1 | K20: AMIELOU JANE G. MENDOZA | L20: Regional Office | M20: Good Condition | N20: 1 | O20: 0 | P20: 0
F21: Sub Total | I21: =SUM(I19:I20) -> 368098.13
B22: IT EQUIPMENT AND SOFTWARE
C23: 01/04/2007 | D23: SERVER, HP PROLIANT (UPGRADED) | E23: 2007-NFA-002-DP-F-001 | F23: ML350G4 | G23: 39086 | H23: pc. | I23: 244431.05 | J23: 1 | K23: ROEL D. CAPERIG | L23: Common Storage Room ( Supply) | M23: Unserviceable | N23: 1 | O23: 0 | P23: 0 | Q23: IIRUP NO. CAR-IIR-2022-C-001 | R23: 50.jpg
D24: B3-420 Notebook 14" Core15-1135g7 / 16B DDR4 / 512GB NVME PCI-E SSD, Intel IRIS XE Graphics, SN# JEXPM22325000059 | E24: 2022-NFA-MSD-DP-T-059 | F24: JEXPM22325000059 | G24: 44883 | H24: set | I24: 56400 | J24: 1 | K24: VERALEW DG. DE VERA | L24: RM's Office | M24: Good Condition | N24: 1 | O24: 0 | P24: 0
D25: CPU, HP Personal Computers | E25: 2005-NFA-OOB-DP-B-005 | G25: 38513 | H25: set | I25: 53665 | J25: 1 | K25: ROEL D. CAPERIG | L25: Common Storage Room ( Supply) | M25: Unserviceable | N25: 1 | O25: 0 | P25: 0 | Q25: IIRUP NO. CAR-IIR-2022-C-002
F26: Sub Total | I26: =SUM(I23:I25) -> 354496.05
B27: FURNITURE, FIXTURES & BOOKS
D28: OFFICE COMBI BLINDS | E28: 2018-NFA-002-FF-L-001 | H28: set | I28: 99971.58 | J28: 1 | K28: AMIELOU JANE G. MENDOZA | L28: Office Lobby | M28: Good Condition | N28: 1 | O28: 0 | P28: 0
D29: =UPPER("12 seater T-shape Conference Table") -> 12 SEATER T-SHAPE CONFERENCE TABLE | E29: 2022-NFA-00B-FF-D-001 | G29: 44208 | H29: set | I29: 97500 | J29: 1 | K29: AMIELOU JANE G. MENDOZA | L29: Conference Room | M29: Good Condition
F30: Sub Total | I30: =SUM(I28:I29) -> 197471.58
A31: 8 | B31: MOTOR VEHICLES, LAND TRANS. EQUIPT AND ACCESORIES
C32: 38737 | D32: TOYOTA INNOVA DSL MODEL 2005 ENGINE # 2KD-9547460 | E32: 2006-NFA-GSD-LT-C-132 | G32: 38737 | H32: unit | I32: 848000 | J32: 1 | K32: JESON JARIOL | L32: Regional Office | M32: Good Condition | N32: 1 | O32: 0 | P32: 0 | R32: 63.jpg
C33: 42636 | D33: ISUZU CROSSWIND SPORTIVO ENGINE # 4JA1M57459 CHASSIS # PABTBBR54FG2089995 | E33: 2016-NFA-GSD-LT-C-203 | G33: 42636 | H33: unit | I33: 1180000 | J33: 1 | K33: ALEXIS M. RAVELO | L33: Regional Office | M33: Good Condition | N33: 1 | O33: 0 | P33: 0 | R33: 64.jpg
D34: 2021 MITSUBISHI STRADA GLS 2.4D 2WD, 4N15UHC6103 SILVER METALIC, AT | E34: 2021-NFA-GSD-LT-C-229 | G34: 44439 | H34: unit | I34: 1397400 | J34: 1 | K34: JOJIT J. CASIO | L34: Regional Office | M34: Good Condition | N34: 1 | O34: 0 | P34: 0
F35: Sub Total | I35: =SUM(I32:I34) -> 3425400
B36: OFFICE EQUIPMENT | O36: 0 | P36: 0
C37: 01/11/2012 | D37: ROOM AIRCONDITIONER, SPLIT TYPE-WALL MOUNTED, 2.0 HP, W/ INVERTER , PANASONIC | E37: 2012-NFA-0B0-OE-C-010 | F37: 2486201743 | G37: 40919 | H37: set | I37: 55000 | J37: 1 | K37: LOVELLA MAY AWING | L37: Acctg. Section | M37: Good Condition | N37: 1 | O37: 0 | P37: 0 | R37: 71.jpg
C38: 41269 | D38: AIRCONDITIONER , PACKED TYPE-FLOOR MOUNTED , 3 TONS, KOPPEL | E38: 2012-NFA-0B0-OE-C-011 | F38: UE323210 | G38: 41269 | H38: set | I38: 81600 | J38: 1 | K38: AMIELOU JANE G. MENDOZA | L38: Office Lobby | M38: Good Condition | N38: 1 | O38: 0 | P38: 0 | R38: 72.jpg
C39: 41269 | D39: AIRCONDITIONER , PACKED TYPE-FLOOR MOUNTED , 3 TONS, KOPPEL | E39: 2012-NFA-0B0-OE-C-013 | F39: KE248331 | G39: 41269 | H39: set | I39: 81600 | J39: 1 | K39: AMIELOU JANE G. MENDOZA | L39: Office Lobby | M39: Good Condition | N39: 1 | O39: 0 | P39: 0 | R39: 74.jpg
C40: 42718 | D40: CHILLER, 2 DOOR SHOWCASE TYPE, CAPACITY 1,000 LTRS | E40: 2016-NFA-00B-OE-T-003 | G40: 42718 | H40: set | I40: 68000 | J40: 1 | K40: GERLIZA L. MULA | L40: TRSD Section | M40: Good Condition | N40: 1 | O40: 0 | P40: 0 | R40: 87.jpg
D41: KOPPEL 3.0 TR FLOOR MOUNTED INVERTER | E41: 2022-NFA-00B-OE-C-020 | G41: 44656 | H41: set | I41: 106000 | J41: 1 | K41: AMIELOU JANE G. MENDOZA | L41: Old RO Office | M41: Good Condition | N41: 1
F42: Sub Total | I42: =SUM(I37:I41) -> 392200
B43: TECHNICAL & SCIENTIFIC EQUIPMENT EQUIPMENT
C44: 08/23/2006 | D44: OHAUS ANALYTICAL BALANCE ADVENTURE 210G X 0.1 MODEL :AR 2140 | E44: 2006-NFA-00B-TS-D-001 | F44: 1227070326 | G44: 38952 | H44: pc. | I44: 80590 | J44: 1 | K44: GERLIZA L. MULA | L44: TRSD Section | M44: Good Condition | N44: 1 | O44: 0 | P44: 0 | R44: 93.jpg
C45: 09/27/2007 | D45: OVEN LABORATORY FOR DRYING BINDER BRAND, GERMANY MODEL;ED 53 | E45: 2007-NFA-TRD-TS-D-315 | F45: 07-17295 | G45: 39352 | H45: pc. | I45: 55000 | J45: 1 | K45: GERLIZA L. MULA | L45: TRSD Section | M45: Good Condition | N45: 1 | O45: 0 | P45: 0 | R45: 100.jpg
C46: 02/21/2011 | D46: LABORATORY SAMPLE GRINDER ROMER MILL SERIES W/ ACCESSORIES | E46: 2011-NFA-TRD-TS-D-1163 | F46: 10050233 | G46: 40595 | H46: pc. | I46: 299500 | J46: 1 | K46: GERLIZA L. MULA | L46: TRSD Section | M46: Good Condition | N46: 1 | O46: 0 | P46: 0 | R46: 97.jpg
C47: 05/02/2017 | D47: ANALYTICAL BALANCE CAPACITY 220G X 0.1MG (BRAND: OHAUS) | E47: 2017-NFA-TRS-TS-D-703 | G47: 42857 | H47: pc. | I47: 63930 | J47: 1 | K47: GERLIZA L. MULA | L47: TRSD Section | M47: Good Condition | N47: 1 | O47: 0 | P47: 0 | R47: 101.jpg
C48: 41591 | D48: LABORATORY POLISHING MACHINE W/ BASIC TOOLS ACCESSORIES | E48: 2013-NFA-TRS-TS-P-008 | F48: S6704/29 | G48: 41591 | H48: set | I48: 248000 | J48: 1 | K48: GERLIZA L. MULA | L48: TRSD Section | M48: Good Condition | N48: 1 | O48: 0 | P48: 0 | R48: 104.jpg
C49: 8/13/2021 | D49: LABORATORY POLISHING MACHINE | E49: 2021-NFA-OCD-TS-P-025 | F49: G2003053 | G49: 44421 | H49: set | I49: 471744 | J49: 1 | K49: GERLIZA L. MULA | L49: TRSD Section | M49: Good Condition | N49: 1 | O49: 0 | P49: 0
C50: 11/24/2021 | D50: LABORATORY HULLER | E50: 2021-NFA-TRS-TS-D-1221 | F50: CB00406 | G50: 44524 | H50: set | I50: 285600 | J50: 1 | K50: GERLIZA L. MULA | L50: TRSD Section | M50: Good Condition | N50: 1 | O50: 0 | P50: 0
F51: Sub Total | I51: =SUM(I44:I50) -> 1504364
B52: PLANT MACHINERY & EQUIPMENT
C53: 1/24/2011 | D53: Generator Set Kubota | E53: 2013-NFA-00B-PE-V-002 | H53: set | I53: 439700 | J53: 1 | K53: ROBERT BACANGGOY | L53: GenSet House | M53: Needing Repair | N53: 1 | O53: 0 | P53: 0
F54: Sub Total | I54: =SUM(I53:I53) -> 439700
I55: =+I17+I21+I26+I30+I35+I42+I51+I54 -> 9941538.3
D57: Certified Correct by: | H57: Approved by: | M57: Verified by: | O57: Verified by:
D60: MARLON O. MARGALLO | H60: VERALEW DG. DE VERA
D61: Assistant Regional Manager | H61: Regional Manager II | M61: COA Representative | O61: COA Representative

Sheet PIF-Fire
A2: NATIONAL FOOD AUTHORITY
A3: Caraga Regional Office
A4: J. Rosales Ave., Butuan City
A5: PROPERTY INVENTORY FORM
A6: As of DECEMBER 31 2022
A7: Schedule of Insurable Property - Fire
A8: Classification / Type | B8: Item Description | C8: Nature of Occupancy1 | D8: Location | E8: Date Constructed / Acquired / Manufactured | F8: Property No. / Other Reference[2] | G8: Valuation | I8: Date of Appraisal | J8: Remarks
G9: Acquisition Cost/ Insurable Interest2 | H9: Market / Appraisal / Insurable Interest2
A10: (1) | B10: (2) | C10: (3) | D10: (4) | E10: (5) | F10: (6) | G10: (7) | H10: (8) | I10: (9) | J10: (10)
A11: PART II - SEMI-EXPENDABLE
A12: MACHINERY AND EQUIPMENT- COMMUNICATION EQUIPMENT
B13: TELEPNHONE SET, CORDLESS, PANASONIC | E13: 40438 | F13: 2010-NFA-00B-CM-D-004 | G13: 2880
B14: FAX MACHINE, KX-FT503CX, PANASONIC | C14: OFFICE | D14: REGIONAL OFFICE | E14: 41365 | F14: 2013-NFA-00B-CM-F-003 | G14: 3896.5
B15: TV, BRAND: DEVANT 22" LCD COLOR MODEL:22DX850 | C15: OFFICE | D15: REGIONAL OFFICE | E15: 40486 | F15: 2010-NFA-00B-CM-G-001 | G15: 10750
B16: DIGITAL VOICE RECORDER SONY BRAND(RECHARGEABLE) | C16: OFFICE | D16: REGIONAL OFFICE | E16: 41551 | F16: 2013-NFA-00B-CM-G-001 | G16: 7900
B17: MICROPHONE, WIRELESS, 2 PCS BRAND: SHURE | C17: OFFICE | D17: REGIONAL OFFICE | E17: 42076 | F17: 2015-NFA-00B-CM-G-004 | G17: 6360
B18: TELEPHONE SET, CORDLESS, PANASONIC | E18: 40941 | F18: 2012-NFA-00B-CM-d-009 | G18: 2075
A19: MACHINERY AND EQUIPMENT- INFORMATION AND COMMUNICATION
B20: CPU, ACER ASPIRE(UPGRADED) | C20: OFFICE | D20: REGIONAL OFFICE | E20: 35915 | F20: 1998-NFA-004-DP-B-007 | G20: 14980
B21: CPU | C21: OFFICE | D21: REGIONAL OFFICE | E21: 40735 | F21: 2011-NFA-00B-DP-B-024 | G21: 8850
B22: UPS, APC | C22: OFFICE | D22: REGIONAL OFFICE | E22: 42818 | F22: 2017-NFA-00B-DP-V-044
B23: PRINTER, EPSON L120 | C23: OFFICE | D23: REGIONAL OFFICE | E23: 42387 | F23: 2016-NFA-00B-DP-D-001 | G23: 5510
B24: PRINTER, EPSON L220 MODEL: C462H | C24: OFFICE | D24: REGIONAL OFFICE | E24: 42387 | F24: 2016-NFA-00B-DP-D-002 | G24: 8475
B25: PRINTER, EPSON L110 | C25: OFFICE | D25: REGIONAL OFFICE | E25: 41947 | F25: 2014-NFA-00B-DP-D-031 | G25: 6143
B26: PRINTER, EPSON 120 | C26: OFFICE | D26: REGIONAL OFFICE | E26: 41822 | F26: 2014-NFA-00B-DP-D-032 | G26: 4976.7
B27: PRINTER, EPSON L120 | C27: OFFICE | D27: REGIONAL OFFICE | E27: 41850 | F27: 2014-NFA-00B-DP-D-034 | G27: 4976.7
B28: PRINTER, EPSON L210 3 IN 1 | C28: OFFICE | D28: REGIONAL OFFICE | E28: 41901 | F28: 2014-NFA-00B-DP-D-035 | G28: 7685
B29: PRINTER, L120 | C29: OFFICE | D29: REGIONAL OFFICE | E29: 42025 | F29: 2015-NFA-00B-DP-D-036 | G29: 5820
B30: PRINTER, EPSON L120 | C30: OFFICE | D30: REGIONAL OFFICE | E30: 42221 | F30: 2015-NFA-00B-DP-D-037 | G30: 4976.7
B31: PRINTER, EPSON L120 | C31: OFFICE | D31: REGIONAL OFFICE | E31: 42299 | F31: 2015-NFA-00B-DP-D-038 | G31: 4976.7
B32: PRINTER, EPSON L120 | C32: OFFICE | D32: REGIONAL OFFICE | E32: 42583 | F32: 2016-NFA-00B-DP-D-039 | G32: 5510
B33: PRINTER, EPSON L220, 3 IN 1 CONTINUOUS INK | C33: OFFICE | D33: REGIONAL OFFICE | E33: 8/22/2017 | F33: 2016-NFA-00B-DP-D-040 | G33: 8475
B34: PRINTER, EPSON L360 | C34: OFFICE | D34: REGIONAL OFFICE | E34: 42695 | F34: 2016-NFA-00B-DP-D-041 | G34: 8475
B35: PRINTER, EPSON L120 | C35: OFFICE | D35: REGIONAL OFFICE | E35: 42818 | F35: 2017-NFA-00B-DP-D-042 | G35: 4870.7
B36: PRINTER, EPSON L360 3 IN 1 | C36: OFFICE | D36: REGIONAL OFFICE | E36: 42818 | F36: 2017-NFA-00B-DP-D-043 | G36: 7580
B37: PRINTER, EPSON L360 | C37: OFFICE | D37: REGIONAL OFFICE | E37: 42849 | F37: 2017-NFA-00B-DP-D-044 | G37: 7579
B38: PRINTER, EPSON L565 MODEL: C463C | C38: OFFICE | D38: REGIONAL OFFICE | E38: 43083 | F38: 2017-NFA-00B-DP-D-045 | G38: 13995
B39: PRINTER, EPSON L565 MODEL: C463C | C39: OFFICE | D39: REGIONAL OFFICE | E39: 43083 | F39: 2017-NFA-00B-DP-D-046 | G39: 13995
B40: PRINTER, EPSON L120 | C40: OFFICE | D40: REGIONAL OFFICE | E40: 43320 | F40: 2018-NFA-00B-DP-D-047 | G40: 5280
B41: PRINTER, EPSON L120 | C41: OFFICE | D41: REGIONAL OFFICE | E41: 43399 | F41: 2018-NFA-00B-DP-D-048 | G41: 5695
B42: PRINTER 3 IN 1 (BROTHER MODEL: DCP-T710W) | C42: OFFICE | D42: REGIONAL OFFICE | E42: 43742 | F42: 2019-NFA-00B-DP-D-049 | G42: 11450
B43: PRINTER EPSON L120 | C43: OFFICE | D43: REGIONAL OFFICE | E43: 43846 | F43: 2020-NFA-00B-DP-D-050 | G43: 4995
B44: PRINTER, EPSON L310 | C44: OFFICE | D44: REGIONAL OFFICE | E44: 43846 | F44: 2020-NFA-00B-DP-D-051 | G44: 7595
B45: PRINTER, EPSON LX+II DOT MATRIX | C45: OFFICE | D45: REGIONAL OFFICE | E45: 39091 | F45: 2007-NFA-MSD-DP-D-330 | G45: 7222.5
... B76: MONITOR ACER LCD MODEL: P166HQL | C76: OFFICE | D76: REGIONAL OFFICE | E76: 38630 | F76: 2005-NFA-004-DP-b-024.1 | G76: 3160.68
A77: FURNITURE, FIXTURES & BOOKS
B78: BED CUSHION, DEW FOAM | E78: 39538 | F78: 2008-NFA-00B-FF-A-002 | G78: 6261
B79: WOODEN BED | C79: OFFICE | D79: REGIONAL OFFICE | E79: 43601 | F79: 2019-NFA-00B-FF-A-003 | G79: 7400
B80: EXECUTIVE TABLE | C80: OFFICE | D80: REGIONAL OFFICE | E80: 39979 | F80: 2009-NFA-00B-FF-B-001 | G80: 8850
B81: EXECUTIVE TABLE | C81: OFFICE | D81: REGIONAL OFFICE | E81: 39979 | F81: 2009-NFA-00B-FF-B-003 | G81: 8850
B82: EXECUTIVE TABLE | C82: OFFICE | D82: REGIONAL OFFICE | E82: 39988 | F82: 2009-NFA-00B-FF-B-004 | G82: 8850
B83: EXECUTIVE TABLE | C83: OFFICE | D83: REGIONAL OFFICE | E83: 39994 | F83: 2009-NFA-00B-FF-B-009 | G83: 8850
B84: TYPING TABLE | C84: OFFICE | D84: REGIONAL OFFICE | E84: 39171 | F84: 2007-NFA-00B-FF-B-009 | G84: 2500
B85: EXECUTIVE TABLE | C85: OFFICE | D85: REGIONAL OFFICE | E85: 39994 | F85: 2009-NFA-00B-FF-B-010 | G85: 8850
B86: EXECUTIVE OFFICE TABLE | C86: OFFICE | D86: REGIONAL OFFICE | E86: 42986 | F86: 2016-NFA-00B-FF-B-011 | G86: 4570
B87: CLERICAL TABLE | C87: OFFICE | D87: REGIONAL OFFICE | E87: 40190 | F87: 2010-NFA-00B-FF-B-027 | G87: 5850
B88: CLERICAL TABLE | C88: OFFICE | D88: REGIONAL OFFICE | E88: 39944 | F88: 2009-NFA-00B-FF-B-028 | G88: 5850
B89: EXECUTIVE TALBE | C89: OFFICE | D89: REGIONAL OFFICE | E89: 1/20/2010 | F89: 2010-NFA-00B-FF-B-030 | G89: 8250
B90: CLERICAL TABLE | C90: OFFICE | D90: REGIONAL OFFICE | E90: 39944 | F90: 2009-NFA-00B-FF-B-031 | G90: 5850
B91: CLERICAL TABLE | C91: OFFICE | D91: REGIONAL OFFICE | E91: 39944 | F91: 2009-NFA-00B-FF-B-032 | G91: 5850
B92: EXECUTIVE TABLE | C92: OFFICE | D92: REGIONAL OFFICE | E92: 40533 | F92: 2010-NFA-00B-FF-B-032 | G92: 6750
B93: CLERICAL TABLE | C93: OFFICE | D93: REGIONAL OFFICE | E93: 39944 | F93: 2009-NFA-00B-FF-B-033 | G93: 5850
B94: CLERICAL TABLE | C94: OFFICE | D94: REGIONAL OFFICE | E94: 39974 | F94: 2009-NFA-00B-FF-B-035 | G94: 5850
B95: CLERICAL TABLE | C95: OFFICE | D95: REGIONAL OFFICE | E95: 39989 | F95: 2009-NFA-00B-FF-B-036 | G95: 5850
B96: CLERICAL TABLE | C96: OFFICE | D96: REGIONAL OFFICE | E96: 39944 | F96: 2009-NFA-00B-FF-B-037 | G96: 5850
B97: EXECUTIVE TABLE(GRAY) | C97: OFFICE | D97: REGIONAL OFFICE | E97: 39979 | F97: 2009-NFA-0B0-FF-B-038 | G97: 8250
B98: CLERICAL TABLE BEIGE | C98: OFFICE | D98: REGIONAL OFFICE | E98: 40602 | F98: 2011-NFA-00B-FF-B-039 | G98: 2215
B99: EXECUTIVE TABLE | C99: OFFICE | D99: REGIONAL OFFICE | E99: 42137 | F99: 2015-NFA-00B-FF-B-040 | G99: 4570
B100: JUNIOR EXECUTIVE TABLE | C100: OFFICE | D100: REGIONAL OFFICE | E100: 42660 | F100: 2016-NFA-00B-FF-B-043 | G100: 3730
B101: JUNIOR EXECUTIVE TABLE | C101: OFFICE | D101: REGIONAL OFFICE | E101: 42660 | F101: 2016-NFA-00B-FF-B-044 | G101: 3730
... B131: SOFA SINGLE SEATER | C131: OFFICE | D131: REGIONAL OFFICE | E131: 42768 | F131: 2017-NFA-00B-FF-I-002 | G131: 8000
B132: SOFA BED,3-4 SEATEARS | C132: OFFICE | D132: REGIONAL OFFICE | E132: 10/17/2016 | F132: 2016-NFA-00B-FF-I-002 | G132: 14300
B133: SOFA SINGLE SEATER | C133: OFFICE | D133: REGIONAL OFFICE | E133: 42768 | F133: 2017-NFA-00B-FF-I-003 | G133: 8000
B134: WOODEN SHELVES(2 UNITS) | C134: OFFICE | D134: REGIONAL OFFICE | E134: 43039 | F134: 2007-NFA-00B-FF-J-002 | G134: 4600
B135: WOODEN OFFICE CABINET | C135: OFFICE | D135: REGIONAL OFFICE | E135: 06/30/2009 | F135: 2009-NFA-00B-FF-J-003 | G135: 3225
B136: WOODEN SHELVES W/ COVER | C136: OFFICE | D136: REGIONAL OFFICE | E136: 39660 | F136: 2008-NFA-00B-FF-J-003 | G136: 6025
B137: WOODEN OFFICE CABINET | C137: OFFICE | D137: REGIONAL OFFICE | E137: 40616 | F137: 2011-NFA-00B-FF-J-005 | G137: 3000
B138: WOODEN CABINET, 3 DOORS | C138: OFFICE | D138: REGIONAL OFFICE | E138: 42660 | F138: 2016-NFA-00B-FF-J-006 | G138: 1275
B139: CABINET DIMENSION: 30" W, 70 "L | C139: OFFICE | D139: REGIONAL OFFICE | E139: 43775 | F139: 2019-NFA-00B-FF-J-007 | G139: 6450
B140: VISITOR'S CHAIR | C140: OFFICE | D140: REGIONAL OFFICE | E140: 39989 | F140: 2009-NFA-00B-FF-K-001 | G140: 1575
B141: VISITOR'S CHAIR | C141: OFFICE | D141: REGIONAL OFFICE | E141: 39979 | F141: 2009-NFA-00B-FF-K-002 | G141: 1575
B142: VISITOR'S CHAIR | C142: OFFICE | D142: REGIONAL OFFICE | E142: 38219 | F142: 2004-NFA-00B-FF-K-002 | G142: 1250
B143: VISITOR'S CHAIR | C143: OFFICE | D143: REGIONAL OFFICE | E143: 42240 | F143: 2015-NFA-00B-FF-K-003 | G143: 1715
B144: VISITOR'S CHAIR | C144: OFFICE | D144: REGIONAL OFFICE | E144: 38219 | F144: 2004-NFA-00B-FF-K-003 | G144: 1250
B145: CENTER TABLE | C145: OFFICE | D145: REGIONAL OFFICE | E145: 39988 | F145: 2009-NFA-00B-F-K-004 | G145: 1851
B146: VISITOR'S CHAIR | C146: OFFICE | D146: REGIONAL OFFICE | E146: 42240 | F146: 2015-NFA-00B-FF-K-004 | G146: 1575
B147: VISITOR'S CHAIR | C147: OFFICE | D147: REGIONAL OFFICE | E147: 42240 | F147: 2015-NFA-00B-FF-K-005 | G147: 1715
... B170: VISITOR'S CHAIR | C170: OFFICE | D170: REGIONAL OFFICE | E170: 37637 | F170: 2003-NFA-00B-FF-b-001.4 | G170: 1635
B171: SR. EXECUTIVE SWIVEL CHAIR | C171: OFFICE | D171: REGIONAL OFFICE | E171: 08/24/2015 | F171: 2015-NFA-00B-FF-K-001 | G171: 4000
B172: SR. EXECUTIVE SWIVEL CHAIR | C172: OFFICE | D172: REGIONAL OFFICE | E172: 42240 | F172: 2015-NFA-00B-FF-K-002 | G172: 4000
B173: HIGH BACK SWIVEL CHAIR W/ ARM REST | C173: OFFICE | D173: REGIONAL OFFICE | E173: 39989 | F173: 2009-NFA-00B-FF-K-019 | G173: 3450
B174: COMPUTER SWIVEL CHAIR | C174: OFFICE | D174: REGIONAL OFFICE | E174: 40603 | F174: 2011-NFA-0B0-FF-K-049 | G174: 855
B175: HIGH BACK SWIVEL CHAIR | C175: OFFICE | D175: REGIONAL OFFICE | E175: 41089 | F175: 2012-NFA-00B-FF-K-055 | G175: 3075
B176: HIGH BACK SWIVEL CHAIR W/ ARM REST | C176: OFFICE | D176: REGIONAL OFFICE | E176: 41458 | F176: 2013-NFA-00B-FF-K-057 | G176: 4770
B177: HIGH BACK SWIVEL CHAIR W/ ARM REST | C177: OFFICE | D177: REGIONAL OFFICE | E177: 41830 | F177: 2014-NFA-00B-FF-K-059 | G177: 3860
B178: COMPUTER SWIVEL CHAIR W/ ARM REST | C178: OFFICE | D178: REGIONAL OFFICE | E178: 42137 | F178: 2015-NFA-00B-FF-K-063 | G178: 2982
B179: COMPUTER SWIVEL CHAIR | C179: OFFICE | D179: REGIONAL OFFICE | E179: 42137 | F179: 2015-NFA-00B-FF-K-066 | G179: 2982
B180: COMPUTER SWIVEL CHAIR W/ ARM REST | C180: OFFICE | D180: REGIONAL OFFICE | E180: 42137 | F180: 2015-NFA-00B-FF-K-067 | G180: 2982
B181: HIGH BACK SWIVEL CHAIR | C181: OFFICE | D181: REGIONAL OFFICE | E181: 42137 | F181: 2015-NFA-00B-FF-K-068 | G181: 7720
B182: COMPUTER SWIVEL CHAIR | C182: OFFICE | D182: REGIONAL OFFICE | E182: 42240 | F182: 2015-NFA-00B-FF-K-071 | G182: 2983
...

Sheet PIF-Floater
A2: NATIONAL FOOD AUTHORITY
A3: Caraga Regional Office
A4: J. Rosales Ave., Butuan City
A5: PROPERTY INVENTORY FORM
A6: As of DECEMBER 31 2022
A7: Schedule of Insurable Property - Floater
A8: Classification / Type | B8: Item Description | C8: Nature of Occupancy1 | D8: Location | E8: Date Constructed / Acquired / Manufactured | F8: Property No. / Other Reference[2] | G8: Valuation | I8: Date of Appraisal | J8: Remarks
G9: Acquisition Cost/ Insurable Interest2 | H9: Market / Appraisal / Insurable Interest2
A10: (1) | B10: (2) | C10: (3) | D10: (4) | E10: (5) | F10: (6) | G10: (7) | H10: (8) | I10: (9) | J10: (10)
A11: PART II - SEMI-EXPENDABLE
A12: MACHINERY AND EQUIPMENT- COMMUNICATION EQUIPMENT
B13: TELEPNHONE SET, CORDLESS, PANASONIC | E13: 40438 | F13: 2010-NFA-00B-CM-D-004 | G13: 2880
B14: FAX MACHINE, KX-FT503CX, PANASONIC | C14: OFFICE | D14: REGIONAL OFFICE | E14: 41365 | F14: 2013-NFA-00B-CM-F-003 | G14: 3896.5
B15: TV, BRAND: DEVANT 22" LCD COLOR MODEL:22DX850 | C15: OFFICE | D15: REGIONAL OFFICE | E15: 40486 | F15: 2010-NFA-00B-CM-G-001 | G15: 10750
B16: DIGITAL VOICE RECORDER SONY BRAND(RECHARGEABLE) | C16: OFFICE | D16: REGIONAL OFFICE | E16: 41551 | F16: 2013-NFA-00B-CM-G-001 | G16: 7900
B17: MICROPHONE, WIRELESS, 2 PCS BRAND: SHURE | C17: OFFICE | D17: REGIONAL OFFICE | E17: 42076 | F17: 2015-NFA-00B-CM-G-004 | G17: 6360
B18: TELEPHONE SET, CORDLESS, PANASONIC | E18: 40941 | F18: 2012-NFA-00B-CM-d-009 | G18: 2075
A19: MACHINERY AND EQUIPMENT- INFORMATION AND COMMUNICATION
B20: CPU, ACER ASPIRE(UPGRADED) | C20: OFFICE | D20: REGIONAL OFFICE | E20: 35915 | F20: 1998-NFA-004-DP-B-007 | G20: 14980
B21: CPU | C21: OFFICE | D21: REGIONAL OFFICE | E21: 40735 | F21: 2011-NFA-00B-DP-B-024 | G21: 8850
B22: UPS, APC | C22: OFFICE | D22: REGIONAL OFFICE | E22: 42818 | F22: 2017-NFA-00B-DP-V-044
B23: PRINTER, EPSON L120 | C23: OFFICE | D23: REGIONAL OFFICE | E23: 42387 | F23: 2016-NFA-00B-DP-D-001 | G23: 5510
B24: PRINTER, EPSON L220 MODEL: C462H | C24: OFFICE | D24: REGIONAL OFFICE | E24: 42387 | F24: 2016-NFA-00B-DP-D-002 | G24: 8475
B25: PRINTER, EPSON L110 | C25: OFFICE | D25: REGIONAL OFFICE | E25: 41947 | F25: 2014-NFA-00B-DP-D-031 | G25: 6143
B26: PRINTER, EPSON 120 | C26: OFFICE | D26: REGIONAL OFFICE | E26: 41822 | F26: 2014-NFA-00B-DP-D-032 | G26: 4976.7
B27: PRINTER, EPSON L120 | C27: OFFICE | D27: REGIONAL OFFICE | E27: 41850 | F27: 2014-NFA-00B-DP-D-034 | G27: 4976.7
B28: PRINTER, EPSON L210 3 IN 1 | C28: OFFICE | D28: REGIONAL OFFICE | E28: 41901 | F28: 2014-NFA-00B-DP-D-035 | G28: 7685
B29: PRINTER, L120 | C29: OFFICE | D29: REGIONAL OFFICE | E29: 42025 | F29: 2015-NFA-00B-DP-D-036 | G29: 5820
B30: PRINTER, EPSON L120 | C30: OFFICE | D30: REGIONAL OFFICE | E30: 42221 | F30: 2015-NFA-00B-DP-D-037 | G30: 4976.7
B31: PRINTER, EPSON L120 | C31: OFFICE | D31: REGIONAL OFFICE | E31: 42299 | F31: 2015-NFA-00B-DP-D-038 | G31: 4976.7
B32: PRINTER, EPSON L120 | C32: OFFICE | D32: REGIONAL OFFICE | E32: 42583 | F32: 2016-NFA-00B-DP-D-039 | G32: 5510
B33: PRINTER, EPSON L220, 3 IN 1 CONTINUOUS INK | C33: OFFICE | D33: REGIONAL OFFICE | E33: 8/22/2017 | F33: 2016-NFA-00B-DP-D-040 | G33: 8475
B34: PRINTER, EPSON L360 | C34: OFFICE | D34: REGIONAL OFFICE | E34: 42695 | F34: 2016-NFA-00B-DP-D-041 | G34: 8475
B35: PRINTER, EPSON L120 | C35: OFFICE | D35: REGIONAL OFFICE | E35: 42818 | F35: 2017-NFA-00B-DP-D-042 | G35: 4870.7
B36: PRINTER, EPSON L360 3 IN 1 | C36: OFFICE | D36: REGIONAL OFFICE | E36: 42818 | F36: 2017-NFA-00B-DP-D-043 | G36: 7580
B37: PRINTER, EPSON L360 | C37: OFFICE | D37: REGIONAL OFFICE | E37: 42849 | F37: 2017-NFA-00B-DP-D-044 | G37: 7579
B38: PRINTER, EPSON L565 MODEL: C463C | C38: OFFICE | D38: REGIONAL OFFICE | E38: 43083 | F38: 2017-NFA-00B-DP-D-045 | G38: 13995
B39: PRINTER, EPSON L565 MODEL: C463C | C39: OFFICE | D39: REGIONAL OFFICE | E39: 43083 | F39: 2017-NFA-00B-DP-D-046 | G39: 13995
B40: PRINTER, EPSON L120 | C40: OFFICE | D40: REGIONAL OFFICE | E40: 43320 | F40: 2018-NFA-00B-DP-D-047 | G40: 5280
B41: PRINTER, EPSON L120 | C41: OFFICE | D41: REGIONAL OFFICE | E41: 43399 | F41: 2018-NFA-00B-DP-D-048 | G41: 5695
B42: PRINTER 3 IN 1 (BROTHER MODEL: DCP-T710W) | C42: OFFICE | D42: REGIONAL OFFICE | E42: 43742 | F42: 2019-NFA-00B-DP-D-049 | G42: 11450
B43: PRINTER EPSON L120 | C43: OFFICE | D43: REGIONAL OFFICE | E43: 43846 | F43: 2020-NFA-00B-DP-D-050 | G43: 4995
B44: PRINTER, EPSON L310 | C44: OFFICE | D44: REGIONAL OFFICE | E44: 43846 | F44: 2020-NFA-00B-DP-D-051 | G44: 7595
B45: PRINTER, EPSON LX+II DOT MATRIX | C45: OFFICE | D45: REGIONAL OFFICE | E45: 39091 | F45: 2007-NFA-MSD-DP-D-330 | G45: 7222.5
... B76: MONITOR ACER LCD MODEL: P166HQL | C76: OFFICE | D76: REGIONAL OFFICE | E76: 38630 | F76: 2005-NFA-004-DP-b-024.1 | G76: 3160.68
A77: FURNITURE, FIXTURES & BOOKS
B78: BED CUSHION, DEW FOAM | E78: 39538 | F78: 2008-NFA-00B-FF-A-002 | G78: 6261
B79: WOODEN BED | C79: OFFICE | D79: REGIONAL OFFICE | E79: 43601 | F79: 2019-NFA-00B-FF-A-003 | G79: 7400
B80: EXECUTIVE TABLE | C80: OFFICE | D80: REGIONAL OFFICE | E80: 39979 | F80: 2009-NFA-00B-FF-B-001 | G80: 8850
B81: EXECUTIVE TABLE | C81: OFFICE | D81: REGIONAL OFFICE | E81: 39979 | F81: 2009-NFA-00B-FF-B-003 | G81: 8850
B82: EXECUTIVE TABLE | C82: OFFICE | D82: REGIONAL OFFICE | E82: 39988 | F82: 2009-NFA-00B-FF-B-004 | G82: 8850
B83: EXECUTIVE TABLE | C83: OFFICE | D83: REGIONAL OFFICE | E83: 39994 | F83: 2009-NFA-00B-FF-B-009 | G83: 8850
B84: TYPING TABLE | C84: OFFICE | D84: REGIONAL OFFICE | E84: 39171 | F84: 2007-NFA-00B-FF-B-009 | G84: 2500
B85: EXECUTIVE TABLE | C85: OFFICE | D85: REGIONAL OFFICE | E85: 39994 | F85: 2009-NFA-00B-FF-B-010 | G85: 8850
B86: EXECUTIVE OFFICE TABLE | C86: OFFICE | D86: REGIONAL OFFICE | E86: 42986 | F86: 2016-NFA-00B-FF-B-011 | G86: 4570
B87: CLERICAL TABLE | C87: OFFICE | D87: REGIONAL OFFICE | E87: 40190 | F87: 2010-NFA-00B-FF-B-027 | G87: 5850
B88: CLERICAL TABLE | C88: OFFICE | D88: REGIONAL OFFICE | E88: 39944 | F88: 2009-NFA-00B-FF-B-028 | G88: 5850
B89: EXECUTIVE TALBE | C89: OFFICE | D89: REGIONAL OFFICE | E89: 1/20/2010 | F89: 2010-NFA-00B-FF-B-030 | G89: 8250
B90: CLERICAL TABLE | C90: OFFICE | D90: REGIONAL OFFICE | E90: 39944 | F90: 2009-NFA-00B-FF-B-031 | G90: 5850
B91: CLERICAL TABLE | C91: OFFICE | D91: REGIONAL OFFICE | E91: 39944 | F91: 2009-NFA-00B-FF-B-032 | G91: 5850
B92: EXECUTIVE TABLE | C92: OFFICE | D92: REGIONAL OFFICE | E92: 40533 | F92: 2010-NFA-00B-FF-B-032 | G92: 6750
B93: CLERICAL TABLE | C93: OFFICE | D93: REGIONAL OFFICE | E93: 39944 | F93: 2009-NFA-00B-FF-B-033 | G93: 5850
B94: CLERICAL TABLE | C94: OFFICE | D94: REGIONAL OFFICE | E94: 39974 | F94: 2009-NFA-00B-FF-B-035 | G94: 5850
B95: CLERICAL TABLE | C95: OFFICE | D95: REGIONAL OFFICE | E95: 39989 | F95: 2009-NFA-00B-FF-B-036 | G95: 5850
B96: CLERICAL TABLE | C96: OFFICE | D96: REGIONAL OFFICE | E96: 39944 | F96: 2009-NFA-00B-FF-B-037 | G96: 5850
B97: EXECUTIVE TABLE(GRAY) | C97: OFFICE | D97: REGIONAL OFFICE | E97: 39979 | F97: 2009-NFA-0B0-FF-B-038 | G97: 8250
B98: CLERICAL TABLE BEIGE | C98: OFFICE | D98: REGIONAL OFFICE | E98: 40602 | F98: 2011-NFA-00B-FF-B-039 | G98: 2215
B99: EXECUTIVE TABLE | C99: OFFICE | D99: REGIONAL OFFICE | E99: 42137 | F99: 2015-NFA-00B-FF-B-040 | G99: 4570
B100: JUNIOR EXECUTIVE TABLE | C100: OFFICE | D100: REGIONAL OFFICE | E100: 42660 | F100: 2016-NFA-00B-FF-B-043 | G100: 3730
B101: JUNIOR EXECUTIVE TABLE | C101: OFFICE | D101: REGIONAL OFFICE | E101: 42660 | F101: 2016-NFA-00B-FF-B-044 | G101: 3730
... B131: SOFA SINGLE SEATER | C131: OFFICE | D131: REGIONAL OFFICE | E131: 42768 | F131: 2017-NFA-00B-FF-I-002 | G131: 8000
B132: SOFA BED,3-4 SEATEARS | C132: OFFICE | D132: REGIONAL OFFICE | E132: 10/17/2016 | F132: 2016-NFA-00B-FF-I-002 | G132: 14300
B133: SOFA SINGLE SEATER | C133: OFFICE | D133: REGIONAL OFFICE | E133: 42768 | F133: 2017-NFA-00B-FF-I-003 | G133: 8000
B134: WOODEN SHELVES(2 UNITS) | C134: OFFICE | D134: REGIONAL OFFICE | E134: 43039 | F134: 2007-NFA-00B-FF-J-002 | G134: 4600
B135: WOODEN OFFICE CABINET | C135: OFFICE | D135: REGIONAL OFFICE | E135: 06/30/2009 | F135: 2009-NFA-00B-FF-J-003 | G135: 3225
B136: WOODEN SHELVES W/ COVER | C136: OFFICE | D136: REGIONAL OFFICE | E136: 39660 | F136: 2008-NFA-00B-FF-J-003 | G136: 6025
B137: WOODEN OFFICE CABINET | C137: OFFICE | D137: REGIONAL OFFICE | E137: 40616 | F137: 2011-NFA-00B-FF-J-005 | G137: 3000
B138: WOODEN CABINET, 3 DOORS | C138: OFFICE | D138: REGIONAL OFFICE | E138: 42660 | F138: 2016-NFA-00B-FF-J-006 | G138: 1275
B139: CABINET DIMENSION: 30" W, 70 "L | C139: OFFICE | D139: REGIONAL OFFICE | E139: 43775 | F139: 2019-NFA-00B-FF-J-007 | G139: 6450
B140: VISITOR'S CHAIR | C140: OFFICE | D140: REGIONAL OFFICE | E140: 39989 | F140: 2009-NFA-00B-FF-K-001 | G140: 1575
B141: VISITOR'S CHAIR | C141: OFFICE | D141: REGIONAL OFFICE | E141: 39979 | F141: 2009-NFA-00B-FF-K-002 | G141: 1575
B142: VISITOR'S CHAIR | C142: OFFICE | D142: REGIONAL OFFICE | E142: 38219 | F142: 2004-NFA-00B-FF-K-002 | G142: 1250
B143: VISITOR'S CHAIR | C143: OFFICE | D143: REGIONAL OFFICE | E143: 42240 | F143: 2015-NFA-00B-FF-K-003 | G143: 1715
B144: VISITOR'S CHAIR | C144: OFFICE | D144: REGIONAL OFFICE | E144: 38219 | F144: 2004-NFA-00B-FF-K-003 | G144: 1250
B145: CENTER TABLE | C145: OFFICE | D145: REGIONAL OFFICE | E145: 39988 | F145: 2009-NFA-00B-F-K-004 | G145: 1851
B146: VISITOR'S CHAIR | C146: OFFICE | D146: REGIONAL OFFICE | E146: 42240 | F146: 2015-NFA-00B-FF-K-004 | G146: 1575
B147: VISITOR'S CHAIR | C147: OFFICE | D147: REGIONAL OFFICE | E147: 42240 | F147: 2015-NFA-00B-FF-K-005 | G147: 1715
... B170: VISITOR'S CHAIR | C170: OFFICE | D170: REGIONAL OFFICE | E170: 37637 | F170: 2003-NFA-00B-FF-b-001.4 | G170: 1635
B171: SR. EXECUTIVE SWIVEL CHAIR | C171: OFFICE | D171: REGIONAL OFFICE | E171: 08/24/2015 | F171: 2015-NFA-00B-FF-K-001 | G171: 4000
B172: SR. EXECUTIVE SWIVEL CHAIR | C172: OFFICE | D172: REGIONAL OFFICE | E172: 42240 | F172: 2015-NFA-00B-FF-K-002 | G172: 4000
B173: HIGH BACK SWIVEL CHAIR W/ ARM REST | C173: OFFICE | D173: REGIONAL OFFICE | E173: 39989 | F173: 2009-NFA-00B-FF-K-019 | G173: 3450
B174: COMPUTER SWIVEL CHAIR | C174: OFFICE | D174: REGIONAL OFFICE | E174: 40603 | F174: 2011-NFA-0B0-FF-K-049 | G174: 855
B175: HIGH BACK SWIVEL CHAIR | C175: OFFICE | D175: REGIONAL OFFICE | E175: 41089 | F175: 2012-NFA-00B-FF-K-055 | G175: 3075
B176: HIGH BACK SWIVEL CHAIR W/ ARM REST | C176: OFFICE | D176: REGIONAL OFFICE | E176: 41458 | F176: 2013-NFA-00B-FF-K-057 | G176: 4770
B177: HIGH BACK SWIVEL CHAIR W/ ARM REST | C177: OFFICE | D177: REGIONAL OFFICE | E177: 41830 | F177: 2014-NFA-00B-FF-K-059 | G177: 3860
B178: COMPUTER SWIVEL CHAIR W/ ARM REST | C178: OFFICE | D178: REGIONAL OFFICE | E178: 42137 | F178: 2015-NFA-00B-FF-K-063 | G178: 2982
B179: COMPUTER SWIVEL CHAIR | C179: OFFICE | D179: REGIONAL OFFICE | E179: 42137 | F179: 2015-NFA-00B-FF-K-066 | G179: 2982
B180: COMPUTER SWIVEL CHAIR W/ ARM REST | C180: OFFICE | D180: REGIONAL OFFICE | E180: 42137 | F180: 2015-NFA-00B-FF-K-067 | G180: 2982
B181: HIGH BACK SWIVEL CHAIR | C181: OFFICE | D181: REGIONAL OFFICE | E181: 42137 | F181: 2015-NFA-00B-FF-K-068 | G181: 7720
B182: COMPUTER SWIVEL CHAIR | C182: OFFICE | D182: REGIONAL OFFICE | E182: 42240 | F182: 2015-NFA-00B-FF-K-071 | G182: 2983
...
